[{"1":[{"9":[{},[7]],".":[{"3":[{"-":[{"h":[{"1":[{"9":[{},[7]]},[7]]},[7]]},[7]]},[7]]},[7]]},[]],"2":[{"a":[{},[11]],"-":[{"d":[{"e":[{"p":[{"e":[{"n":[{"d":[{"e":[{"n":[{"t":[{},[12]]},[12]]},[12]]},[12]]},[12]]},[12]]},[12]]},[12]]},[12]]},[12]]},[]],"3":[{"-":[{"h":[{"1":[{"9":[{},[7]]},[7]]},[7]]},[7]],"f":[{},[22]]},[]],"4":[{"-":[{"m":[{"y":[{"c":[{"n":[{},[5]]},[5]]},[5]]},[5]]},[5]],"(":[{"+":[{")":[{},[21]]},[21]]},[21]]},[]],"5":[{"7":[{"k":[{"i":[{"p":[{"2":[{},[29]]},[29]]},[29]]},[29]]},[29]]},[]],"7":[{"k":[{"i":[{"p":[{"2":[{},[29]]},[29]]},[29]]},[29]]},[]],"9":[{},[]],"t":[{"h":[{"1":[{},[11]],"e":[{"l":[{"i":[{"a":[{"l":[{},[7]]},[7]]},[7]]},[7]],"r":[{"a":[{"p":[{"y":[{},[10]]},[10]]},[10]]},[10]]},[0,1,5,7,9,10,15,16,18,19,21,23,26,27,28,32]],"r":[{"o":[{"u":[{"g":[{"h":[{},[7,22]]},[7,22]]},[7,22]],"p":[{"o":[{"i":[{"e":[{"s":[{"i":[{"s":[{},[31]]},[31]]},[31]]},[31]]},[31]]},[31]]},[31]]},[7,22,31]]},[7,22,31]]},[0,1,5,7,9,10,11,15,16,18,19,21,22,23,26,27,28,31,32]],"i":[{"o":[{"n":[{",":[{},[13,30]],":":[{},[15]],"a":[{"l":[{},[22]]},[22]]},[0,3,4,7,10,11,12,13,14,15,17,21,22,23,26,28,30]]},[0,3,4,7,10,11,12,13,14,15,17,21,22,23,26,28,30]],"g":[{"e":[{"n":[{},[0]]},[0]]},[0]],"f":[{"i":[{"e":[{"s":[{},[0,5]]},[0,5]]},[0,5]]},[0,5]],"e":[{"n":[{"t":[{"s":[{},[1]]},[1]]},[1]]},[1]],"v":[{"e":[{},[5,31]],"a":[{"t":[{"i":[{"o":[{"n":[{},[12,17]]},[12,17]]},[12,17]]},[12,17]]},[12,17]]},[5,12,17,31]],"n":[{"i":[{},[6]],"g":[{},[28]],"o":[{"b":[{"l":[{"a":[{"s":[{"t":[{"o":[{"m":[{"a":[{},[31,32]]},[31,32]]},[31,32]]},[31,32]]},[31,32]]},[31,32]]},[31,32]]},[31,32]]},[31,32]]},[6,9,23,26,28,31,32]],"c":[{},[9]],"a":[{"t":[{"i":[{"o":[{"n":[{":":[{},[15]],",":[{},[30]]},[11,15,23,26,30]]},[11,15,23,26,30]]},[11,15,23,26,30]]},[11,15,23,26,30]],"l":[{},[23]]},[11,15,23,26,30]]},[0,1,3,4,5,6,7,9,10,11,12,13,14,15,17,21,22,23,26,28,30,31,32]],"y":[{"p":[{"e":[{},[13]]},[13]]},[0,2,13,27]],"e":[{"s":[{},[0,9,22,30,31,32]],"i":[{"n":[{"s":[{":":[{},[16]]},[4,16,19,29,32]]},[4,16,19,21,26,29,32]]},[4,16,19,21,26,29,32]],"a":[{"d":[{"4":[{"-":[{"m":[{"y":[{"c":[{"n":[{},[5]]},[5]]},[5]]},[5]]},[5]]},[5]]},[5]]},[5]],"n":[{"a":[{"n":[{"c":[{"e":[{},[9]]},[9]]},[9]]},[9]]},[9]],"m":[{"n":[{"e":[{"s":[{"s":[{},[19]]},[19]]},[19]]},[19]]},[9,16,19]],"c":[{"t":[{"i":[{"o":[{"n":[{",":[{},[13]]},[13,14]]},[13,14]]},[13,14]]},[13,14]]},[13,14]],"r":[{"i":[{"z":[{"a":[{"t":[{"i":[{"o":[{"n":[{",":[{},[13]]},[13]]},[13]]},[13]]},[13]]},[13]]},[13]]},[13]]},[13,16]]},[0,4,5,9,13,14,16,19,21,22,26,29,30,31,32]],"r":[{"a":[{"t":[{"e":[{"s":[{},[0]]},[0]]},[0]],"n":[{"s":[{"c":[{"r":[{"i":[{"p":[{"t":[{"o":[{"m":[{"e":[{},[2]]},[2]]},[2]],"i":[{"o":[{"n":[{"a":[{"l":[{},[22]]},[22]]},[4,21,22]]},[4,21,22]]},[4,21,22]]},[2,4,21,22]]},[2,4,21,22]]},[2,4,21,22]]},[2,4,21,22]]},[2,4,21,22]],"f":[{"o":[{"r":[{"m":[{"a":[{"t":[{"i":[{"o":[{"n":[{},[7,17]]},[7,17]]},[7,17]]},[7,17]]},[7,17]],"i":[{"n":[{"g":[{},[20]]},[20]]},[20]]},[7,17,20]]},[7,17,20]]},[7,17,20]]},[7,17,20]]},[2,4,7,17,20,21,22]]},[2,4,7,17,20,21,22]]},[0,2,4,7,17,20,21,22]],"i":[{"g":[{"g":[{"e":[{"r":[{"i":[{"n":[{"g":[{},[17]]},[17]]},[17]]},[17]]},[17]]},[17]]},[17]]},[17]],"o":[{"l":[{"s":[{},[26]]},[26,27]]},[26,27]],"c":[{"p":[{"‐":[{"r":[{"e":[{"s":[{"t":[{"‐":[{"m":[{"a":[{"d":[{"2":[{},[27]]},[27]]},[27]]},[27]]},[27]]},[27]]},[27]]},[27]]},[27]]},[27]]},[27]]},[27]]},[0,2,4,7,17,20,21,22,26,27]],"o":[{"m":[{"a":[{"s":[{},[0]]},[0,5,10,20,31,32]],"e":[{},[2]]},[0,2,5,10,20,31,32]],"s":[{"i":[{"s":[{},[1]]},[1]]},[1]],"r":[{"y":[{},[5]],"s":[{},[16,21]]},[4,5,16,21]],"b":[{"a":[{"-":[{"j":[{"o":[{"h":[{"n":[{"s":[{"o":[{"n":[{},[6]]},[6]]},[6]]},[6]]},[6]]},[6]]},[6]]},[6]]},[6]]},[6]],"n":[{"e":[{},[7]]},[7]],"p":[{"o":[{"i":[{"e":[{"t":[{"i":[{"c":[{},[9]]},[9]]},[9]]},[9]]},[9]]},[9]]},[9]],"o":[{"l":[{},[14]]},[14]]},[0,1,2,4,5,6,7,9,10,11,14,16,19,20,21,23,29,31,32]],"s":[{"c":[{"h":[{},[24]]},[24]]},[1,4,11,24]],"a":[{"t":[{"i":[{"o":[{"n":[{},[3,14]]},[3,14]]},[3,14]]},[3,14]],"l":[{"a":[{},[6]]},[6,31]],"n":[{"o":[{},[6]],"t":[{},[30]]},[6,30]],"r":[{"i":[{},[6]],"g":[{"e":[{"t":[{},[32]]},[32]]},[32]]},[6,32]],"i":[{"n":[{"s":[{},[7]],"e":[{"d":[{},[18]]},[18]]},[7,18]]},[7,18]],"c":[{"c":[{},[8,13,20]]},[8,13,20]],"b":[{"i":[{"l":[{"i":[{"z":[{"i":[{"n":[{"g":[{},[26]]},[26]]},[26]]},[26]],"t":[{"y":[{},[27]]},[27]]},[26,27]]},[26,27]]},[26,27]]},[26,27]],"‐":[{"t":[{"r":[{"c":[{"p":[{"‐":[{"r":[{"e":[{"s":[{"t":[{"‐":[{"m":[{"a":[{"d":[{"2":[{},[27]]},[27]]},[27]]},[27]]},[27]]},[27]]},[27]]},[27]]},[27]]},[27]]},[27]]},[27]]},[27]]},[27]]},[27]]},[3,6,7,8,13,14,18,20,26,27,30,31,32]],"t":[{"i":[{"n":[{"i":[{},[6]]},[6]]},[6]],"a":[{},[6]]},[6]],"u":[{"m":[{"o":[{"r":[{},[7,22,30]],"u":[{"r":[{},[16]]},[16]]},[7,16,22,30]]},[7,16,22,30]]},[7,16,22,30]],"m":[{"e":[{"n":[{"t":[{},[9]]},[9]]},[9]]},[9]],"f":[{"h":[{},[11]]},[11]],",":[{},[25]],"‐":[{"d":[{"o":[{"m":[{"a":[{"i":[{"n":[{},[26]]},[26]]},[26]]},[26]]},[26]]},[26]],"m":[{"a":[{"d":[{"2":[{},[27]]},[27]]},[27]]},[27]]},[26,27]]},[]],"h":[{"1":[{"9":[{},[7]],".":[{"3":[{"-":[{"h":[{"1":[{"9":[{},[7]]},[7]]},[7]]},[7]]},[7]]},[7]]},[7,11]],"e":[{"l":[{"i":[{"a":[{"l":[{},[7]]},[7]]},[7]]},[7]],"m":[{"a":[{"t":[{"o":[{"p":[{"o":[{"i":[{"e":[{"t":[{"i":[{"c":[{},[9]]},[9]]},[9]]},[9]]},[9]]},[9]]},[9]]},[9]]},[9]]},[9]]},[9]],"r":[{"a":[{"p":[{"y":[{},[10]]},[10]]},[10]]},[10]],"n":[{"s":[{"i":[{"v":[{"e":[{},[14]]},[14]]},[14]]},[14]]},[14]],"c":[{"t":[{"‐":[{"d":[{"o":[{"m":[{"a":[{"i":[{"n":[{},[26]]},[26]]},[26]]},[26]]},[26]]},[26]]},[26]]},[26]]},[26]]},[0,1,5,7,9,10,14,15,16,18,19,21,23,26,27,28,32]],"o":[{"c":[{"y":[{"t":[{"e":[{},[0,4]]},[0,4]]},[0,4]]},[0,4]],"r":[{"d":[{"o":[{"i":[{"d":[{},[3]]},[3]]},[3]]},[3]],"t":[{},[5]],"a":[{"g":[{"e":[{},[19]]},[19]]},[19]],"i":[{"n":[{},[22]]},[22]]},[3,5,19,22]],"i":[{"d":[{},[9]]},[9]],"a":[{},[17]]},[0,3,4,5,9,17,19,22]],"i":[{"g":[{"h":[{"-":[{"g":[{"r":[{"a":[{"d":[{"e":[{},[2,18]]},[2,18]]},[2,18]]},[2,18]]},[2,18]],"r":[{"i":[{"s":[{"k":[{},[5]]},[5]]},[5]]},[5]]},[2,5,18]]},[2,5,18]]},[2,5,18]],"s":[{"t":[{"o":[{"n":[{"e":[{},[7]]},[7]]},[7]]},[7]]},[7]],"b":[{"i":[{"t":[{"s":[{},[11]],"i":[{"o":[{"n":[{},[13]]},[13]]},[13]]},[11,13]]},[11,13]]},[11,13]]},[2,5,6,7,11,13,18]],"-":[{"g":[{"r":[{"a":[{"d":[{"e":[{},[2,18]]},[2,18]]},[2,18]]},[2,18]]},[2,18]],"r":[{"i":[{"s":[{"k":[{},[5]]},[5]]},[5]]},[5]]},[2,5,18]],"a":[{"l":[{"l":[{"m":[{"a":[{"r":[{"k":[{},[3]]},[3]]},[3]]},[3]]},[3]]},[3]],"n":[{"g":[{},[6]],"i":[{"s":[{"m":[{},[12]]},[12]]},[12]]},[6,12]],"r":[{"a":[{"c":[{"t":[{"e":[{"r":[{"i":[{"z":[{"a":[{"t":[{"i":[{"o":[{"n":[{",":[{},[13]]},[13]]},[13]]},[13]]},[13]]},[13]]},[13]]},[13]]},[13]]},[13]]},[13]]},[13]]},[13]]},[13]],"s":[{"e":[{},[28]]},[28]],"g":[{"e":[{"s":[{},[31]]},[31]]},[31]]},[3,6,12,13,28,31]],",":[{},[6,24]],"t":[{"a":[{"r":[{"i":[{},[6]]},[6]]},[6]]},[6]],"n":[{"s":[{"o":[{"n":[{},[6]]},[6]]},[6]]},[6]],"u":[{"a":[{"n":[{"g":[{},[6]]},[6]]},[6]],"w":[{"e":[{"1":[{},[7,9,23,26]]},[7,9,23,26]]},[7,9,23,26]],"m":[{"a":[{"n":[{},[8,20]]},[8,20]]},[8,20]]},[6,7,8,9,20,23,26]],"r":[{"o":[{"u":[{"g":[{"h":[{},[7,22]]},[7,22]]},[7,22]],"n":[{"i":[{"z":[{"e":[{},[19,23]]},[19,23]]},[19,23]]},[19,23]],"m":[{"o":[{"s":[{"o":[{"m":[{"e":[{},[27]]},[27]]},[27]]},[27]]},[27]]},[27]],"p":[{"o":[{"i":[{"e":[{"s":[{"i":[{"s":[{},[31]]},[31]]},[31]]},[31]]},[31]]},[31]]},[31]]},[7,19,22,23,27,31]]},[7,19,22,23,27,31]],"l":[{},[12]],"p":[{"n":[{"2":[{},[17]]},[17]]},[17]],"y":[{"m":[{"a":[{"l":[{},[17,18]]},[17,18]]},[17,18]]},[17,18]]},[]],"e":[{"1":[{},[7,9,23,26]],"2":[{"a":[{},[11]]},[11]],"o":[{"a":[{"n":[{"t":[{"i":[{"g":[{"e":[{"n":[{},[0]]},[0]]},[0]]},[0]]},[0]]},[0]]},[0]]},[0]],"n":[{"t":[{"i":[{"f":[{"i":[{"e":[{"s":[{},[0,5]]},[0,5]]},[0,5]]},[0,5]],"a":[{"t":[{"i":[{"o":[{"n":[{":":[{},[15]]},[11,15,23,26]]},[11,15,23,26]]},[11,15,23,26]]},[11,15,23,26]],"l":[{},[23]]},[11,15,23,26]]},[0,5,11,15,23,26]],"s":[{},[1,4]]},[0,1,3,4,5,9,11,12,15,21,23,26]],"f":[{"o":[{"r":[{"c":[{"i":[{"n":[{"g":[{},[4]]},[4]]},[4]]},[4]]},[4]]},[4]]},[4]],"e":[{"s":[{"s":[{},[16]],"i":[{"s":[{},[30]]},[30]]},[16,20,30]]},[4,8,14,16,20,30]],"i":[{"t":[{"o":[{"b":[{"a":[{"-":[{"j":[{"o":[{"h":[{"n":[{"s":[{"o":[{"n":[{},[6]]},[6]]},[6]]},[6]]},[6]]},[6]]},[6]]},[6]]},[6]]},[6]]},[6]]},[6]]},[6]],"a":[{"n":[{"c":[{"e":[{},[9]]},[9]]},[9]]},[9]],"d":[{"e":[{"n":[{"t":[{},[12]]},[12]]},[12]]},[12]],"s":[{"i":[{"v":[{"e":[{},[14]]},[14]]},[14]]},[14]],"c":[{"h":[{"y":[{"m":[{"a":[{"l":[{},[17,18]]},[17,18]]},[17,18]]},[17,18]]},[17,18]]},[17,18]]},[0,1,3,4,5,6,8,9,11,12,14,15,16,17,18,20,21,23,26,30]],"s":[{"t":[{"a":[{"b":[{"i":[{"l":[{"i":[{"z":[{"i":[{"n":[{"g":[{},[26]]},[26]]},[26]]},[26]]},[26]]},[26]]},[26]]},[26]]},[26]],"‐":[{"m":[{"a":[{"d":[{"2":[{},[27]]},[27]]},[27]]},[27]]},[27]]},[0,26,27]],"s":[{"i":[{"v":[{"e":[{"n":[{"e":[{"s":[{"s":[{},[16]]},[16]]},[16]]},[16]]},[16]]},[16]],"o":[{"n":[{},[22]]},[22]],"n":[{"g":[{},[31]]},[31]]},[16,22,31]],"e":[{"n":[{"t":[{"i":[{"a":[{"l":[{},[23]]},[23]]},[23]]},[23]]},[23]]},[23]]},[11,16,19,22,23,31]],"e":[{"n":[{"c":[{"h":[{"y":[{"m":[{"a":[{"l":[{},[17,18]]},[17,18]]},[17,18]]},[17,18]]},[17,18]]},[17,18]]},[17,18]]},[17,18]],"i":[{"s":[{},[30,31]]},[30,31]]},[0,5,9,11,16,17,18,19,20,22,23,26,27,28,30,31,32]],"c":[{"u":[{"l":[{"a":[{"r":[{},[1]]},[1]]},[1]],"r":[{"r":[{"e":[{"n":[{"t":[{},[3]]},[3]]},[3]]},[3]]},[3]]},[1,3]],"c":[{"a":[{"r":[{"e":[{"l":[{"l":[{"i":[{},[6]]},[6]]},[6]]},[6]]},[6]]},[6]]},[6]],"h":[{"a":[{"n":[{"i":[{"s":[{"m":[{},[12]]},[12]]},[12]]},[12]]},[12]]},[12]],"t":[{"i":[{"o":[{"n":[{",":[{},[13]]},[13,14]]},[13,14]]},[13,14]],"‐":[{"d":[{"o":[{"m":[{"a":[{"i":[{"n":[{},[26]]},[26]]},[26]]},[26]]},[26]]},[26]]},[26]]},[13,14,26]]},[1,3,6,12,13,14,26]],"u":[{"r":[{"o":[{"f":[{"i":[{"b":[{"r":[{"o":[{"m":[{"a":[{"t":[{"o":[{"s":[{"i":[{"s":[{},[1]]},[1]]},[1]]},[1]]},[1]]},[1]]},[1]]},[1]]},[1]]},[1]]},[1]]},[1]],"b":[{"l":[{"a":[{"s":[{"t":[{"o":[{"m":[{"a":[{},[5]]},[5]]},[5]]},[5]]},[5]]},[5]]},[5]]},[5]],"n":[{"a":[{"l":[{},[23]]},[23]]},[23]]},[1,5,23]],"a":[{"l":[{},[19,26,29]]},[19,26,29]]},[1,5,19,23,26,29]]},[1,5,19,23,26,29]],"-":[{"c":[{"e":[{"l":[{"l":[{},[2]]},[2]]},[2]]},[2]]},[2]],"l":[{"l":[{"i":[{},[6]],"a":[{},[6,24,25]],"s":[{},[9,16,19,21,29]],"u":[{"m":[{},[23]]},[23]]},[2,4,6,7,9,16,19,21,22,23,24,25,28,29]],"o":[{"p":[{"m":[{"e":[{"n":[{"t":[{},[4,21]]},[4,21]]},[4,21]]},[4,21]],"i":[{"n":[{"g":[{},[23]]},[23]]},[23]]},[4,21,23]]},[4,21,23]],"e":[{"m":[{"e":[{"n":[{"t":[{},[5]]},[5]]},[5]]},[5]],"n":[{"i":[{"t":[{"o":[{"b":[{"a":[{"-":[{"j":[{"o":[{"h":[{"n":[{"s":[{"o":[{"n":[{},[6]]},[6]]},[6]]},[6]]},[6]]},[6]]},[6]]},[6]]},[6]]},[6]]},[6]]},[6]]},[6]]},[6]]},[5,6]],"i":[{"a":[{"l":[{},[7]]},[7]]},[7]]},[2,4,5,6,7,9,16,19,21,22,23,24,25,28,29]],"a":[{"g":[{"e":[{},[2,21]]},[2,21]],"d":[{"4":[{"-":[{"m":[{"y":[{"c":[{"n":[{},[5]]},[5]]},[5]]},[5]]},[5]]},[5]]},[5]]},[2,5,21]],"r":[{"s":[{"i":[{"t":[{"y":[{},[2]]},[2]]},[2]]},[2]],"i":[{"c":[{"k":[{},[6]]},[6]],"z":[{"a":[{"t":[{"i":[{"o":[{"n":[{",":[{},[13]]},[13]]},[13]]},[13]]},[13]]},[13]]},[13]],"n":[{"g":[{},[17]]},[17]]},[6,13,17]],"u":[{"l":[{"o":[{},[6]]},[6]]},[6]],"a":[{"p":[{"y":[{},[10]]},[10]],"t":[{"i":[{"o":[{"n":[{},[26,30]]},[26,30]]},[26,30]]},[26,30]]},[10,26,30]],"e":[{"n":[{"t":[{"i":[{"a":[{"t":[{"i":[{"o":[{"n":[{":":[{},[15]]},[11,15,23,26]]},[11,15,23,26]]},[11,15,23,26]]},[11,15,23,26]]},[11,15,23,26]]},[11,15,23,26]]},[11,15,23,26]]},[11,15,23,26]],"b":[{"e":[{"l":[{"l":[{"u":[{"m":[{},[23]]},[23]]},[23]]},[23]]},[23]]},[23]]},[11,15,23,26]],"g":[{"e":[{},[29]]},[29]],"y":[{"t":[{"h":[{"r":[{"o":[{"p":[{"o":[{"i":[{"e":[{"s":[{"i":[{"s":[{},[31]]},[31]]},[31]]},[31]]},[31]]},[31]]},[31]]},[31]]},[31]]},[31]]},[31]]},[31]]},[2,6,10,11,12,13,14,15,16,17,23,26,29,30,31]],"v":[{"e":[{"n":[{"t":[{"s":[{},[4]]},[4]]},[4]],"l":[{"o":[{"p":[{"m":[{"e":[{"n":[{"t":[{},[4,21]]},[4,21]]},[4,21]]},[4,21]],"i":[{"n":[{"g":[{},[23]]},[23]]},[23]]},[4,21,23]]},[4,21,23]]},[4,21,23]]},[4,21,23]],"o":[{"l":[{"u":[{"t":[{"i":[{"o":[{"n":[{},[10]]},[10]]},[10]]},[10]]},[10]]},[10]]},[10]]},[4,10,21,23]],"i":[{"n":[{"s":[{":":[{},[16]]},[4,16,19,29,32]],"f":[{"o":[{"r":[{"c":[{"e":[{"s":[{},[11]]},[11]]},[11]]},[11]]},[11]]},[11]]},[4,11,16,19,21,26,29,32]]},[4,11,16,19,21,26,29,32]],"e":[{"d":[{"b":[{"a":[{"c":[{"k":[{},[5]]},[5]]},[5]]},[5]]},[5]]},[5,6]],"d":[{"b":[{"a":[{"c":[{"k":[{},[5]]},[5]]},[5]]},[5]],"e":[{"r":[{"i":[{"c":[{"k":[{},[6]]},[6]]},[6]]},[6]]},[6]],"i":[{"c":[{"t":[{"i":[{"o":[{"n":[{},[14]]},[14]]},[14]]},[14]]},[14]],"a":[{"t":[{"e":[{"s":[{},[30,32]]},[30,32]]},[30,32]]},[30,32]]},[14,30,32]]},[5,6,14,18,21,30,32]],"g":[{"u":[{"l":[{"a":[{"t":[{"o":[{"r":[{"y":[{},[5]],"s":[{},[16]]},[5,16]]},[5,16]],"e":[{"s":[{},[9]]},[9,29]]},[5,9,16,29]]},[5,9,16,29]]},[5,9,16,29]]},[5,9,16,29]],"a":[{"s":[{"u":[{"s":[{":":[{},[14]]},[14]]},[14]]},[14]]},[14]],"r":[{"a":[{"d":[{"a":[{"t":[{"i":[{"o":[{"n":[{},[28]]},[28]]},[28]]},[28]]},[28]]},[28]]},[28]]},[28]]},[5,9,14,16,28,29]],"m":[{"e":[{"n":[{"t":[{},[5]]},[5]]},[5]],"a":[{"t":[{"o":[{"p":[{"o":[{"i":[{"e":[{"t":[{"i":[{"c":[{},[9]]},[9]]},[9]]},[9]]},[9]]},[9]]},[9]]},[9]]},[9]],"p":[{"h":[{"o":[{"r":[{"i":[{"n":[{},[22]]},[22]]},[22]]},[22]]},[22]]},[22]]},[9,22]],"n":[{"e":[{"s":[{"s":[{},[19]]},[19]]},[19]]},[19]],"o":[{"t":[{},[25]]},[25]]},[5,9,16,19,22,25]],"w":[{"i":[{"s":[{},[6]]},[6]]},[6]],"p":[{"i":[{"t":[{"h":[{"e":[{"l":[{"i":[{"a":[{"l":[{},[7]]},[7]]},[7]]},[7]]},[7]]},[7]]},[7]]},[7]],"r":[{"e":[{"s":[{"s":[{"i":[{"o":[{"n":[{},[22]]},[22]],"n":[{"g":[{},[31]]},[31]]},[22,31]]},[11,22,31]]},[11,22,31]]},[11,22,31]]},[11,22,31]],"e":[{"n":[{"d":[{"e":[{"n":[{"t":[{},[12]]},[12]]},[12]]},[12]]},[12]]},[12]]},[7,11,12,22,31]],"t":[{"i":[{"c":[{},[9]],"n":[{"o":[{"b":[{"l":[{"a":[{"s":[{"t":[{"o":[{"m":[{"a":[{},[31,32]]},[31,32]]},[31,32]]},[31,32]]},[31,32]]},[31,32]]},[31,32]]},[31,32]]},[31,32]]},[31,32]]},[9,31,32]],"e":[{"c":[{"t":[{"i":[{"o":[{"n":[{",":[{},[13]]},[13,14]]},[13,14]]},[13,14]]},[13,14]]},[13,14]]},[13,14]],"s":[{"c":[{"h":[{},[24]]},[24]]},[24]],"a":[{"‐":[{"t":[{"r":[{"c":[{"p":[{"‐":[{"r":[{"e":[{"s":[{"t":[{"‐":[{"m":[{"a":[{"d":[{"2":[{},[27]]},[27]]},[27]]},[27]]},[27]]},[27]]},[27]]},[27]]},[27]]},[27]]},[27]]},[27]]},[27]]},[27]]},[27]],"l":[{},[31]]},[27,31]]},[9,13,14,24,27,31,32]],"h":[{"e":[{"n":[{"s":[{"i":[{"v":[{"e":[{},[14]]},[14]]},[14]]},[14]]},[14]]},[14]]},[14]],"q":[{"u":[{"i":[{"r":[{"e":[{"d":[{},[21]]},[21]]},[21]]},[21]]},[21]]},[21]],"b":[{"e":[{"l":[{"l":[{"u":[{"m":[{},[23]]},[23]]},[23]]},[23]]},[23]]},[23]],"x":[{"i":[{"t":[{},[28]]},[28]]},[28]],"f":[{"i":[{"n":[{"i":[{"t":[{"i":[{"v":[{"e":[{},[31]]},[31]]},[31]]},[31]]},[31]]},[31]]},[31]]},[31]]},[]],"c":[{"o":[{"m":[{"b":[{"i":[{"n":[{"a":[{"t":[{"i":[{"o":[{"n":[{},[0]]},[0]]},[0]]},[0]]},[0]]},[0]]},[0]]},[0]],"m":[{"i":[{"t":[{"m":[{"e":[{"n":[{"t":[{},[9]]},[9]]},[9]]},[9]]},[9]]},[9]]},[9]],"p":[{"r":[{"e":[{"h":[{"e":[{"n":[{"s":[{"i":[{"v":[{"e":[{},[14]]},[14]]},[14]]},[14]]},[14]]},[14]]},[14]]},[14]]},[14]],"l":[{"e":[{"x":[{},[28]]},[28]]},[28]]},[14,28]]},[0,9,14,28]],"h":[{"o":[{"r":[{"t":[{},[5]]},[5]]},[5]]},[5]],"r":[{"e":[{},[5]]},[5]],"l":[{"m":[{"a":[{"n":[{},[24]]},[24]]},[24]]},[24]],"n":[{"t":[{"r":[{"o":[{"l":[{"s":[{},[26]]},[26,27]]},[26,27]]},[26,27]]},[26,27]],"c":[{"o":[{"p":[{"r":[{"o":[{"t":[{"e":[{"i":[{"n":[{},[26]]},[26]]},[26]]},[26]]},[26]]},[26]]},[26]]},[26]]},[26]],"v":[{"e":[{"r":[{"g":[{"e":[{},[29]]},[29]]},[29]]},[29]]},[29]]},[26,27,29]],"p":[{"r":[{"o":[{"t":[{"e":[{"i":[{"n":[{"s":[{},[32]]},[26,32]]},[26,32]]},[26,32]]},[26,32]]},[26,32]]},[26,32]]},[26,32]],"u":[{"p":[{"l":[{"e":[{"s":[{},[28]]},[28]]},[28]]},[28]]},[28]]},[0,5,9,14,24,26,27,28,29,32]],"y":[{"t":[{"e":[{},[0,4]]},[0,4]],"c":[{"l":[{"e":[{},[28,29]]},[28,29]]},[28,29]]},[0,4,28,29]],"u":[{"l":[{"a":[{"r":[{},[1]]},[1]]},[1]],"r":[{"r":[{"e":[{"n":[{"t":[{},[3,15]]},[3,15]]},[3,15]]},[3,15]]},[3,15]]},[1,3,15]],"a":[{"p":[{"e":[{},[1]]},[1]],"s":[{"t":[{"a":[{"n":[{"o":[{},[6]]},[6]]},[6]]},[6]],"c":[{"a":[{"d":[{"e":[{},[7]]},[7]]},[7]]},[7]]},[6,7]],"r":[{"e":[{"l":[{"l":[{"i":[{},[6]]},[6]]},[6]]},[6]]},[6]],"d":[{"e":[{},[7]]},[7]],"n":[{"c":[{"e":[{"r":[{},[12,14,16]]},[12,14,16]]},[12,14,16]]},[12,14,16]],"l":[{"i":[{"f":[{"a":[{"n":[{"o":[{},[24,25]]},[24,25]]},[24,25]]},[24,25]]},[24,25]]},[24,25]]},[1,3,6,7,12,14,16,24,25]],"e":[{"l":[{"l":[{"s":[{},[9,16,19,21,29]]},[2,4,7,9,16,19,21,22,28,29]]},[2,4,7,9,16,19,21,22,28,29]],"r":[{"u":[{"l":[{"o":[{},[6]]},[6]]},[6]],"e":[{"b":[{"e":[{"l":[{"l":[{"u":[{"m":[{},[23]]},[23]]},[23]]},[23]]},[23]]},[23]]},[23]]},[6,12,14,16,23]],"c":[{"c":[{"a":[{"r":[{"e":[{"l":[{"l":[{"i":[{},[6]]},[6]]},[6]]},[6]]},[6]]},[6]]},[6]]},[6]],"s":[{},[11]]},[2,4,6,7,9,11,12,14,16,19,21,22,23,28,29,30]],"r":[{"i":[{"p":[{"t":[{"o":[{"m":[{"e":[{},[2]]},[2]]},[2]],"i":[{"o":[{"n":[{"a":[{"l":[{},[22]]},[22]]},[4,21,22]]},[4,21,22]]},[4,21,22]]},[2,4,21,22]]},[2,4,21,22]]},[2,4,21,22]],"o":[{"s":[{"s":[{"-":[{"c":[{"o":[{"h":[{"o":[{"r":[{"t":[{},[5]]},[5]]},[5]]},[5]]},[5]]},[5]]},[5]]},[5]]},[5]],"p":[{"h":[{"a":[{"g":[{"e":[{"s":[{},[31]]},[31]]},[31]]},[31]]},[31]]},[31]]},[5,31]]},[2,4,5,21,22,31]],"h":[{"o":[{"r":[{"d":[{"o":[{"i":[{"d":[{},[3]]},[3]]},[3]]},[3]],"a":[{"g":[{"e":[{},[19]]},[19]]},[19]]},[3,19]]},[3,19]],"a":[{"n":[{"i":[{"s":[{"m":[{},[12]]},[12]]},[12]]},[12]],"r":[{"a":[{"c":[{"t":[{"e":[{"r":[{"i":[{"z":[{"a":[{"t":[{"i":[{"o":[{"n":[{",":[{},[13]]},[13]]},[13]]},[13]]},[13]]},[13]]},[13]]},[13]]},[13]]},[13]]},[13]]},[13]]},[13]]},[13]]},[12,13]],"y":[{"m":[{"a":[{"l":[{},[17,18]]},[17,18]]},[17,18]]},[17,18]],"r":[{"o":[{"n":[{"i":[{"z":[{"e":[{},[19,23]]},[19,23]]},[19,23]]},[19,23]],"m":[{"o":[{"s":[{"o":[{"m":[{"e":[{},[27]]},[27]]},[27]]},[27]]},[27]]},[27]]},[19,23,27]]},[19,23,27]],"e":[{},[19]]},[3,12,13,17,18,19,23,24,27]],"t":[{"o":[{"r":[{"s":[{},[21]]},[4,21]]},[4,21]],"i":[{"v":[{"a":[{"t":[{"i":[{"o":[{"n":[{},[12,17]]},[12,17]]},[12,17]]},[12,17]]},[12,17]]},[12,17]],"o":[{"n":[{",":[{},[13]]},[13,14]]},[13,14]]},[12,13,14,17]],"e":[{"r":[{"i":[{"z":[{"a":[{"t":[{"i":[{"o":[{"n":[{",":[{},[13]]},[13]]},[13]]},[13]]},[13]]},[13]]},[13]]},[13]]},[13]]},[13]],"‐":[{"d":[{"o":[{"m":[{"a":[{"i":[{"n":[{},[26]]},[26]]},[26]]},[26]]},[26]]},[26]]},[26]]},[4,12,13,14,17,21,26]],"i":[{"n":[{"g":[{},[4]]},[4]]},[4]],"n":[{},[5]],"k":[{},[5,6]],"m":[{",":[{},[6]]},[6]],"c":[{"a":[{"r":[{"e":[{"l":[{"l":[{"i":[{},[6]]},[6]]},[6]]},[6]]},[6]]},[6]]},[6,8,13,20]],"l":[{"o":[{"n":[{"a":[{"l":[{},[10]]},[10]]},[10]]},[10]],"e":[{},[28,29]]},[10,28,29]],"d":[{"4":[{"(":[{"+":[{")":[{},[21]]},[21]]},[21]]},[21]]},[21]],"p":[{"‐":[{"r":[{"e":[{"s":[{"t":[{"‐":[{"m":[{"a":[{"d":[{"2":[{},[27]]},[27]]},[27]]},[27]]},[27]]},[27]]},[27]]},[27]]},[27]]},[27]]},[27]]},[]],"o":[{"m":[{"b":[{"i":[{"n":[{"a":[{"t":[{"i":[{"o":[{"n":[{},[0]]},[0]]},[0]]},[0]]},[0]]},[0]]},[0]]},[0]],"a":[{"s":[{},[0,3]],"t":[{"o":[{"s":[{"i":[{"s":[{},[1]]},[1]]},[1]]},[1]]},[1]],"i":[{"n":[{},[26]]},[26]]},[0,1,2,3,5,8,10,13,17,18,20,26,31,32]],"e":[{},[2,27]],"m":[{"i":[{"t":[{"m":[{"e":[{"n":[{"t":[{},[9]]},[9]]},[9]]},[9]]},[9]]},[9]]},[9]],"p":[{"r":[{"e":[{"h":[{"e":[{"n":[{"s":[{"i":[{"v":[{"e":[{},[14]]},[14]]},[14]]},[14]]},[14]]},[14]]},[14]]},[14]]},[14]],"l":[{"e":[{"x":[{},[28]]},[28]]},[28]]},[14,28]],"o":[{"t":[{"e":[{"s":[{},[22,31]]},[22,31]],"i":[{"n":[{"g":[{},[28]]},[28]]},[28]]},[22,28,31]],"s":[{"o":[{"m":[{"e":[{},[27]]},[27]]},[27]]},[27]]},[22,27,28,31]]},[0,1,2,3,4,5,8,9,10,13,14,17,18,20,22,26,27,28,31,32]],"n":[{"g":[{"e":[{"s":[{"t":[{},[0]]},[0]]},[0]]},[0]],"e":[{},[6,7,24,25]],"s":[{},[8,13,14,20]],"a":[{"l":[{},[10,22,23,28]]},[10,22,23,28]],",":[{},[13,30]],":":[{},[15]],"i":[{"z":[{"e":[{},[19,23]]},[19,23]]},[19,23]],"t":[{"r":[{"o":[{"l":[{"s":[{},[26]]},[26,27]]},[26,27]]},[26,27]]},[26,27]],"c":[{"o":[{"p":[{"r":[{"o":[{"t":[{"e":[{"i":[{"n":[{"s":[{},[32]]},[26,32]]},[26,32]]},[26,32]]},[26,32]]},[26,32]]},[26,32]]},[26,32]]},[26,32]]},[26,32]],"v":[{"e":[{"r":[{"g":[{"e":[{},[29]]},[29]]},[29]]},[29]]},[29]]},[0,3,4,6,7,8,10,11,12,13,14,15,17,19,20,21,22,23,24,25,26,27,28,29,30,32]],"f":[{"i":[{"b":[{"r":[{"o":[{"m":[{"a":[{"t":[{"o":[{"s":[{"i":[{"s":[{},[1]]},[1]]},[1]]},[1]]},[1]]},[1]]},[1]]},[1]]},[1]]},[1]]},[1]],"a":[{"n":[{"o":[{},[6]]},[6]]},[6]]},[0,1,2,3,5,6,9,10,13,14,16,19,20,21,22,27,28,32]],"a":[{"n":[{"t":[{"i":[{"g":[{"e":[{"n":[{},[0]]},[0]]},[0]]},[0]]},[0]]},[0]]},[0,17]],"c":[{"y":[{"t":[{"e":[{},[0,4]]},[0,4]]},[0,4]]},[0,4]],"b":[{"l":[{"a":[{"s":[{"t":[{"o":[{"m":[{"a":[{"s":[{},[0]]},[0,5,10,20,31,32]]},[0,5,10,20,31,32]]},[0,5,10,20,31,32]]},[0,5,10,20,31,32]]},[0,5,10,20,31,32]]},[0,5,10,20,31,32]]},[0,5,10,20,31,32]],"a":[{"-":[{"j":[{"o":[{"h":[{"n":[{"s":[{"o":[{"n":[{},[6]]},[6]]},[6]]},[6]]},[6]]},[6]]},[6]]},[6]]},[6]]},[0,5,6,10,20,31,32]],"l":[{"e":[{"c":[{"u":[{"l":[{"a":[{"r":[{},[1]]},[1]]},[1]]},[1]]},[1]]},[1]],"l":[{"a":[{"n":[{"d":[{},[6]]},[6]]},[6]]},[6]],"u":[{"t":[{"i":[{"o":[{"n":[{},[10]]},[10]]},[10]]},[10]]},[10]],"m":[{"a":[{"n":[{},[24]]},[24]]},[24]],"s":[{},[26]],"i":[{"f":[{"e":[{"r":[{"a":[{"t":[{"i":[{"o":[{"n":[{},[26,30]]},[26,30]]},[26,30]]},[26,30]]},[26,30]]},[26,30]]},[26,30]]},[26,30]]},[26,30]]},[1,6,10,14,24,26,27,30]],"s":[{"i":[{"s":[{},[1]],"t":[{"i":[{"v":[{"e":[{},[5]]},[5]]},[5]]},[5]]},[1,5]],"s":[{"-":[{"c":[{"o":[{"h":[{"o":[{"r":[{"t":[{},[5]]},[5]]},[5]]},[5]]},[5]]},[5]]},[5]]},[5]],"o":[{"m":[{"e":[{},[27]]},[27]]},[27]]},[1,5,27]],"i":[{"n":[{"t":[{},[3]],"g":[{},[15]]},[3,15]],"d":[{},[3,9]],"e":[{"t":[{"i":[{"c":[{},[9]]},[9]]},[9]],"s":[{"i":[{"s":[{},[31]]},[31]]},[31]]},[9,31]]},[3,9,15,31]],"r":[{"d":[{"o":[{"i":[{"d":[{},[3]]},[3]]},[3]]},[3]],"c":[{"i":[{"n":[{"g":[{},[4]]},[4]]},[4]],"e":[{"s":[{},[11]]},[11]]},[4,11]],"t":[{},[5]],"e":[{"l":[{"l":[{"a":[{},[6,24,25]]},[6,24,25]]},[6,24,25]]},[5,6,24,25]],"y":[{},[5]],"m":[{"a":[{"l":[{},[7]],"t":[{"i":[{"o":[{"n":[{},[7,17]]},[7,17]]},[7,17]]},[7,17]]},[7,17]],"i":[{"n":[{"g":[{},[20]]},[20]]},[20]]},[7,17,20]],"s":[{},[16,21]],"a":[{"g":[{"e":[{},[19]]},[19]]},[19]],"i":[{"n":[{},[22]]},[22]]},[3,4,5,6,7,11,12,14,16,17,19,20,21,22,24,25,30]],"t":[{"e":[{"i":[{"n":[{"s":[{":":[{},[16]]},[4,16,19,29,32]]},[4,16,19,21,26,29,32]]},[4,16,19,21,26,29,32]],"s":[{},[22,31]]},[4,16,19,21,22,26,29,31,32]],"t":[{"a":[{},[6]]},[6]],"a":[{"t":[{"i":[{"o":[{"n":[{},[14]]},[14]]},[14]]},[14]]},[14]],"i":[{"n":[{"g":[{},[28]]},[28]]},[28]]},[4,6,14,16,19,21,22,25,26,28,29,31,32]],"g":[{"r":[{"a":[{"m":[{},[4]]},[4]]},[4]],"e":[{"n":[{"e":[{"s":[{"i":[{"s":[{},[30]]},[30]]},[30]]},[30]]},[30]]},[30]]},[4,30]],"p":[{"m":[{"e":[{"n":[{"t":[{},[4,21]]},[4,21]]},[4,21]]},[4,21]],"o":[{"i":[{"e":[{"t":[{"i":[{"c":[{},[9]]},[9]]},[9]],"s":[{"i":[{"s":[{},[31]]},[31]]},[31]]},[9,31]]},[9,31]]},[9,31]],"i":[{"n":[{"g":[{},[23]]},[23]]},[23]],"r":[{"o":[{"t":[{"e":[{"i":[{"n":[{"s":[{},[32]]},[26,32]]},[26,32]]},[26,32]]},[26,32]]},[26,32]]},[26,32]],"h":[{"a":[{"g":[{"e":[{"s":[{},[31]]},[31]]},[31]]},[31]]},[31]]},[4,5,9,21,23,26,31,32]],"h":[{"o":[{"r":[{"t":[{},[5]]},[5]]},[5]],"n":[{"s":[{"o":[{"n":[{},[6]]},[6]]},[6]]},[6]]},[5,6]],"o":[{"p":[{},[5]],"l":[{},[14]]},[5,14]],"k":[{"h":[{"t":[{"a":[{"r":[{"i":[{},[6]]},[6]]},[6]]},[6]]},[6]]},[6]],"v":[{"a":[{"r":[{"i":[{"a":[{"n":[{},[7]]},[7]]},[7]]},[7]]},[7]]},[7]],"w":[{"t":[{"h":[{},[7,28]]},[7,28]]},[7,28]],"u":[{"g":[{"h":[{},[7,22]]},[7,22]],"r":[{},[16]],"p":[{"l":[{"e":[{"s":[{},[28]]},[28]]},[28]]},[28]]},[7,16,22,28]],"e":[{"t":[{"s":[{"c":[{"h":[{},[24]]},[24]]},[24]]},[24]]},[24]]},[]],"m":[{"b":[{"i":[{"n":[{"a":[{"t":[{"i":[{"o":[{"n":[{},[0]]},[0]]},[0]]},[0]]},[0]]},[0]]},[0]]},[0]],"p":[{"h":[{"o":[{"c":[{"y":[{"t":[{"e":[{},[0,4]]},[0,4]]},[0,4]]},[0,4]],"i":[{"d":[{},[9]]},[9]]},[0,4,9]]},[0,4,9]],"r":[{"e":[{"h":[{"e":[{"n":[{"s":[{"i":[{"v":[{"e":[{},[14]]},[14]]},[14]]},[14]]},[14]]},[14]]},[14]]},[14]]},[14]],"l":[{"e":[{"x":[{},[28]]},[28]]},[28]]},[0,4,9,14,28]],"a":[{"s":[{"t":[{"e":[{"r":[{},[16]]},[16]]},[16]]},[0,3,16]],"t":[{"o":[{"s":[{"i":[{"s":[{},[1]]},[1]]},[1]],"p":[{"o":[{"i":[{"e":[{"t":[{"i":[{"c":[{},[9]]},[9]]},[9]]},[9]]},[9]]},[9]]},[9]]},[1,9]],"i":[{"o":[{"n":[{},[7,17]]},[7,17]]},[7,17]]},[1,7,9,17]],"r":[{"k":[{},[3]]},[3]],"l":[{"l":[{},[6]],"i":[{"g":[{"n":[{"a":[{"n":[{"t":[{},[17]]},[17]]},[17]]},[17]]},[17]]},[17]]},[6,7,17,18]],"n":[{},[8,20,24]],"i":[{"n":[{"t":[{"e":[{"n":[{"a":[{"n":[{"c":[{"e":[{},[9]]},[9]]},[9]]},[9]]},[9]]},[9]],"a":[{"i":[{"n":[{"e":[{"d":[{},[18]]},[18]]},[18]]},[18]]},[18]]},[9,18]]},[9,18,26]]},[9,18,26]],"p":[{"h":[{"o":[{"r":[{"i":[{"n":[{},[22]]},[22]]},[22]]},[22]]},[22]]},[22]],"d":[{"2":[{},[27]]},[27]],"c":[{"r":[{"o":[{"p":[{"h":[{"a":[{"g":[{"e":[{"s":[{},[31]]},[31]]},[31]]},[31]]},[31]]},[31]]},[31]]},[31]]},[31]]},[0,1,2,3,5,6,7,8,9,10,13,16,17,18,20,22,24,26,27,31,32]],"o":[{"l":[{"e":[{"c":[{"u":[{"l":[{"a":[{"r":[{},[1]]},[1]]},[1]]},[1]]},[1]]},[1]]},[1]],"k":[{"h":[{"t":[{"a":[{"r":[{"i":[{},[6]]},[6]]},[6]]},[6]]},[6]]},[6]],"r":[{},[7,22,30]],"u":[{"r":[{},[16]]},[16]],"t":[{"e":[{"s":[{},[22,31]]},[22,31]],"i":[{"n":[{"g":[{},[28]]},[28]]},[28]]},[22,25,28,31]],"s":[{"o":[{"m":[{"e":[{},[27]]},[27]]},[27]]},[27]]},[1,6,7,16,22,25,27,28,30,31]],"e":[{"n":[{"t":[{},[4,5,9,21]]},[4,5,9,21]],"c":[{"h":[{"a":[{"n":[{"i":[{"s":[{"m":[{},[12]]},[12]]},[12]]},[12]]},[12]]},[12]]},[12]],"s":[{"e":[{"n":[{"c":[{"h":[{"y":[{"m":[{"a":[{"l":[{},[17,18]]},[17,18]]},[17,18]]},[17,18]]},[17,18]]},[17,18]]},[17,18]]},[17,18]]},[17,18]],"d":[{"i":[{"a":[{"t":[{"e":[{"s":[{},[30,32]]},[30,32]]},[30,32]]},[30,32]]},[30,32]]},[30,32]]},[2,4,5,9,12,17,18,21,27,30,32]],"u":[{"t":[{"a":[{"t":[{"i":[{"o":[{"n":[{},[3]]},[3]]},[3]]},[3]],"n":[{"t":[{},[30]]},[30]]},[3,30]]},[3,30]]},[3,30]],"y":[{"c":[{"n":[{},[5]],"o":[{"n":[{"c":[{"o":[{"p":[{"r":[{"o":[{"t":[{"e":[{"i":[{"n":[{},[26]]},[26]]},[26]]},[26]]},[26]]},[26]]},[26]]},[26]]},[26]]},[26]]},[26]]},[5,15,26,32]]},[5,15,26,32]],",":[{},[6]],"v":[{",":[{},[6]]},[6]],"m":[{"i":[{"t":[{"m":[{"e":[{"n":[{"t":[{},[9]]},[9]]},[9]]},[9]]},[9]]},[9]]},[9]],"i":[{"t":[{"m":[{"e":[{"n":[{"t":[{},[9]]},[9]]},[9]]},[9]]},[9]],"n":[{"g":[{},[20]]},[20]],"g":[{"r":[{"a":[{"t":[{"i":[{"o":[{"n":[{},[22]]},[22]]},[22]]},[22]]},[22]]},[22]]},[22]],"c":[{"e":[{},[30]]},[30]]},[9,20,22,30]],"n":[{"e":[{"s":[{"s":[{},[19]]},[19]]},[19]]},[19]]},[]],"b":[{"i":[{"n":[{"a":[{"t":[{"i":[{"o":[{"n":[{},[0]]},[0]]},[0]]},[0]]},[0]]},[0]],"q":[{"u":[{"i":[{"t":[{"i":[{"n":[{},[9,23,26]]},[9,23,26]]},[9,23,26]]},[9,23,26]]},[9,23,26]]},[9,23,26]],"t":[{"s":[{},[11]],"i":[{"o":[{"n":[{},[13]]},[13]]},[13]]},[11,13]],"l":[{"i":[{"z":[{"i":[{"n":[{"g":[{},[26]]},[26]]},[26]]},[26]],"t":[{"y":[{},[27]]},[27]]},[26,27]]},[26,27]]},[0,9,11,13,23,26,27]],"l":[{"a":[{"s":[{"t":[{"o":[{"m":[{"a":[{"s":[{},[0]]},[0,5,10,20,31,32]]},[0,5,10,20,31,32]]},[0,5,10,20,31,32]]},[0,5,10,20,31,32]]},[0,5,10,20,31,32]]},[0,5,10,20,31,32]]},[0,5,10,20,31,32]],"r":[{"o":[{"m":[{"a":[{"t":[{"o":[{"s":[{"i":[{"s":[{},[1]]},[1]]},[1]]},[1]]},[1]]},[1]]},[1]]},[1]]},[1]],"a":[{"c":[{"k":[{},[5]]},[5]],"-":[{"j":[{"o":[{"h":[{"n":[{"s":[{"o":[{"n":[{},[6]]},[6]]},[6]]},[6]]},[6]]},[6]]},[6]]},[6]]},[5,6]],",":[{},[6]],"y":[{},[17,18,26,27,28,31,32]],"e":[{"l":[{"l":[{"u":[{"m":[{},[23]]},[23]]},[23]]},[23]],"t":[{"a":[{"‐":[{"t":[{"r":[{"c":[{"p":[{"‐":[{"r":[{"e":[{"s":[{"t":[{"‐":[{"m":[{"a":[{"d":[{"2":[{},[27]]},[27]]},[27]]},[27]]},[27]]},[27]]},[27]]},[27]]},[27]]},[27]]},[27]]},[27]]},[27]]},[27]]},[27]]},[27]]},[27]]},[23,27]]},[]],"i":[{"n":[{"a":[{"t":[{"i":[{"o":[{"n":[{},[0]]},[0]]},[0]]},[0]],"c":[{"t":[{"i":[{"v":[{"a":[{"t":[{"i":[{"o":[{"n":[{},[12]]},[12]]},[12]]},[12]]},[12]]},[12]]},[12]]},[12]]},[12]]},[0,12]],"f":[{"i":[{"l":[{"t":[{"r":[{"a":[{"t":[{"e":[{"s":[{},[0]]},[0]]},[0]]},[0]]},[0]]},[0]]},[0]]},[0]],"o":[{"r":[{"c":[{"e":[{"s":[{},[11]]},[11]]},[11]]},[11]]},[11]]},[0,11]],"g":[{"l":[{"e":[{"-":[{"c":[{"e":[{"l":[{"l":[{},[2]]},[2]]},[2]]},[2]]},[2]]},[2]]},[2]]},[2,4,15,17,20,23,26,28,31,32]],"e":[{"a":[{"g":[{"e":[{},[2,21]]},[2,21]]},[2,21]],"d":[{},[18]]},[2,18,21]],"t":[{"e":[{"n":[{"a":[{"n":[{"c":[{"e":[{},[9]]},[9]]},[9]]},[9]]},[9]]},[9]],"a":[{"i":[{"n":[{"e":[{"d":[{},[18]]},[18]]},[18]]},[18]]},[18]]},[3,9,18]],"s":[{"t":[{},[15]],":":[{},[16]]},[4,7,15,16,19,29,32]],"i":[{"t":[{"i":[{"a":[{"t":[{"i":[{"o":[{"n":[{",":[{},[30]]},[30]]},[30]]},[30]]},[30]]},[30]],"v":[{"e":[{},[31]]},[31]]},[30,31]]},[30,31]]},[6,30,31]],"h":[{"i":[{"b":[{"i":[{"t":[{"s":[{},[11]],"i":[{"o":[{"n":[{},[13]]},[13]]},[13]]},[11,13]]},[11,13]]},[11,13]]},[11,13]]},[11,13]],"v":[{"a":[{"s":[{"i":[{"o":[{"n":[{},[22]]},[22]]},[22]]},[22]]},[22]]},[22]],"o":[{"b":[{"l":[{"a":[{"s":[{"t":[{"o":[{"m":[{"a":[{},[31,32]]},[31,32]]},[31,32]]},[31,32]]},[31,32]]},[31,32]]},[31,32]]},[31,32]]},[31,32]]},[0,1,2,3,4,6,7,8,9,11,12,13,14,15,16,17,18,19,20,21,22,23,26,28,29,30,31,32]],"o":[{"n":[{"s":[{},[8,13,14,20]],",":[{},[13,30]],":":[{},[15]],"a":[{"l":[{},[22]]},[22]]},[0,3,4,7,8,10,11,12,13,14,15,17,20,21,22,23,26,28,30]],"b":[{"l":[{"a":[{"s":[{"t":[{"o":[{"m":[{"a":[{"s":[{},[0]]},[0,10,20]]},[0,10,20]]},[0,10,20]]},[0,10,20]]},[0,10,20]]},[0,10,20]]},[0,10,20]]},[0,10,20]],"m":[{"a":[{"s":[{},[3]]},[1,2,3,8,13,17,18]]},[1,2,3,8,13,17,18]],"g":[{"e":[{"n":[{"e":[{"s":[{"i":[{"s":[{},[30]]},[30]]},[30]]},[30]]},[30]]},[30]]},[30]]},[0,1,2,3,4,7,8,10,11,12,13,14,15,17,18,20,21,22,23,26,28,30]],"g":[{"e":[{"n":[{},[0]]},[0]],"h":[{"-":[{"g":[{"r":[{"a":[{"d":[{"e":[{},[2,18]]},[2,18]]},[2,18]]},[2,18]]},[2,18]],"r":[{"i":[{"s":[{"k":[{},[5]]},[5]]},[5]]},[5]]},[2,5,18]]},[2,5,18]],"a":[{"s":[{"e":[{},[9,23,26]]},[9,23,26]]},[9,23,26]],"n":[{"a":[{"n":[{"t":[{},[17]]},[17]],"l":[{"l":[{"i":[{"n":[{"g":[{},[32]]},[32]]},[32]]},[32]]},[32]]},[17,32]]},[17,32]],"g":[{"e":[{"r":[{"i":[{"n":[{"g":[{},[17]]},[17]]},[17]]},[17]]},[17]]},[17]],"r":[{"a":[{"t":[{"i":[{"o":[{"n":[{},[22]]},[22]]},[22]]},[22]]},[22]]},[22]]},[0,2,5,9,17,18,22,23,25,26,32]],"t":[{"y":[{},[0,2,27]],"h":[{"e":[{"l":[{"i":[{"a":[{"l":[{},[7]]},[7]]},[7]]},[7]]},[7]]},[0,1,7]],"i":[{"v":[{"e":[{},[5,31]]},[5,31]],"n":[{},[9,23,26]],"o":[{"n":[{},[13]]},[13]],"a":[{"t":[{"i":[{"o":[{"n":[{",":[{},[30]]},[30]]},[30]]},[30]]},[30]]},[30]]},[5,9,13,23,26,30,31]],"o":[{"b":[{"a":[{"-":[{"j":[{"o":[{"h":[{"n":[{"s":[{"o":[{"n":[{},[6]]},[6]]},[6]]},[6]]},[6]]},[6]]},[6]]},[6]]},[6]]},[6]]},[6]],"m":[{"e":[{"n":[{"t":[{},[9]]},[9]]},[9]]},[9]],"s":[{},[11]]},[0,1,2,5,6,7,9,11,13,23,26,27,28,30,31]],"l":[{"t":[{"r":[{"a":[{"t":[{"e":[{"s":[{},[0]]},[0]]},[0]]},[0]]},[0]]},[0]],"d":[{"-":[{"t":[{"y":[{"p":[{"e":[{},[13]]},[13]]},[13]]},[13]]},[13]]},[13]],"l":[{"e":[{"m":[{"o":[{"t":[{},[25]]},[25]]},[25]]},[25]]},[25]],"i":[{"z":[{"i":[{"n":[{"g":[{},[26]]},[26]]},[26]]},[26]],"t":[{"y":[{},[27]]},[27]]},[26,27]]},[0,13,25,26,27]],"d":[{"2":[{"-":[{"d":[{"e":[{"p":[{"e":[{"n":[{"d":[{"e":[{"n":[{"t":[{},[12]]},[12]]},[12]]},[12]]},[12]]},[12]]},[12]]},[12]]},[12]]},[12]]},[4,11,12,22,28,29,30,31,32]],"e":[{"n":[{"t":[{"i":[{"f":[{"i":[{"e":[{"s":[{},[0,5]]},[0,5]]},[0,5]]},[0,5]]},[0,5]]},[0,5]]},[0,5]]},[0,5]],"h":[{},[13]],"-":[{"r":[{"a":[{"p":[{"1":[{},[18]]},[18]]},[18]]},[18]]},[18]]},[0,3,4,5,9,11,12,13,16,18,19,22,28,29,30,31,32]],"f":[{"i":[{"e":[{"s":[{},[0,5]]},[0,5]]},[0,5]],"f":[{"e":[{"r":[{"e":[{"n":[{"t":[{"i":[{"a":[{"t":[{"i":[{"o":[{"n":[{":":[{},[15]]},[11,15,23,26]]},[11,15,23,26]]},[11,15,23,26]]},[11,15,23,26]]},[11,15,23,26]]},[11,15,23,26]]},[11,15,23,26]]},[11,15,23,26]]},[11,15,23,26]]},[11,15,23,26]]},[11,15,23,26]]},[11,15,23,26]],"a":[{"n":[{"o":[{},[24,25]]},[24,25]]},[24,25]],"e":[{"r":[{"a":[{"t":[{"i":[{"o":[{"n":[{},[26,30]]},[26,30]]},[26,30]]},[26,30]]},[26,30]]},[26,30]]},[26,30]]},[0,5,11,15,23,24,25,26,30]],"e":[{"s":[{"i":[{"s":[{},[31]]},[31]]},[0,5,31]],"n":[{"t":[{"s":[{},[1]]},[1]]},[1]],"t":[{"i":[{"c":[{},[9]]},[9]]},[9]]},[0,1,5,9,31]],"v":[{"a":[{"l":[{},[0]],"t":[{"i":[{"o":[{"n":[{},[12,17]]},[12,17]]},[12,17]]},[12,17]]},[0,12,17]],"e":[{"r":[{"s":[{"i":[{"t":[{"y":[{},[2]]},[2]]},[2]]},[2]]},[2,14,31]],"n":[{"e":[{"s":[{"s":[{},[16]]},[16]]},[16]]},[16]],"s":[{},[17]]},[2,5,14,16,17,31]]},[0,2,5,12,14,16,17,31]],"b":[{"r":[{"o":[{"m":[{"a":[{"t":[{"o":[{"s":[{"i":[{"s":[{},[1]]},[1]]},[1]]},[1]]},[1]]},[1]]},[1]]},[1]]},[1]],"i":[{"t":[{"s":[{},[11]],"i":[{"o":[{"n":[{},[13]]},[13]]},[13]]},[11,13]]},[11,13]]},[1,11,13]],"s":[{"k":[{},[5]],"t":[{"o":[{"n":[{"e":[{},[7]]},[7]]},[7]]},[7]],"m":[{},[12]]},[1,2,3,5,6,7,12,18,23,27,30,31,32]],"p":[{"2":[{},[29]],"t":[{"o":[{"m":[{"e":[{},[2]]},[2]]},[2]],"i":[{"o":[{"n":[{"a":[{"l":[{},[22]]},[22]]},[4,21,22]]},[4,21,22]]},[4,21,22]]},[2,4,21,22]]},[2,4,21,22,29]],"c":[{"k":[{},[6]],"t":[{"i":[{"o":[{"n":[{},[14]]},[14]]},[14]]},[14]],"h":[{"e":[{},[19]]},[19]],"e":[{},[30]]},[6,9,14,19,30]],"a":[{"v":[{"a":[{"r":[{"o":[{"n":[{"e":[{},[6,24,25]]},[6,24,25]]},[6,24,25]]},[6,24,25]]},[6,24,25]]},[6,24,25]],"n":[{},[7]],"l":[{},[7,23]],"t":[{"i":[{"o":[{"n":[{":":[{},[15]],",":[{},[30]]},[11,15,23,26,30]]},[11,15,23,26,30]]},[11,15,23,26,30]],"e":[{"s":[{},[30,32]]},[30,32]]},[11,15,23,26,30,32]]},[6,7,11,15,23,24,25,26,30,32]],"q":[{"u":[{"i":[{"t":[{"i":[{"n":[{},[9,23,26]]},[9,23,26]]},[9,23,26]]},[9,23,26]]},[9,23,26]]},[9,23,26]],"z":[{"a":[{"t":[{"i":[{"o":[{"n":[{",":[{},[13]]},[13]]},[13]]},[13]]},[13]]},[13]],"e":[{},[19,23]],"i":[{"n":[{"g":[{},[26]]},[26]]},[26]]},[13,19,23,26]],"r":[{"e":[{"d":[{},[21]]},[21]]},[21]]},[]],"n":[{"2":[{},[17]],"a":[{"t":[{"i":[{"o":[{"n":[{},[0]]},[0]]},[0]]},[0]],"l":[{"y":[{"s":[{"i":[{"s":[{},[2,5]]},[2,5]]},[2,5]]},[2,5]],"l":[{"i":[{"n":[{"g":[{},[32]]},[32]]},[32]]},[32]]},[2,5,10,22,23,28,32]],"ï":[{"v":[{"e":[{},[4]]},[4]]},[4]],"n":[{"c":[{"e":[{},[9]]},[9]],"t":[{},[17]]},[9,17]],"c":[{"t":[{"i":[{"v":[{"a":[{"t":[{"i":[{"o":[{"n":[{},[12]]},[12]]},[12]]},[12]]},[12]]},[12]]},[12]]},[12]]},[12]],"p":[{"h":[{"a":[{"s":[{"e":[{},[28]]},[28]]},[28]]},[28]]},[28]]},[0,2,4,5,9,10,12,17,22,23,28,32]],"e":[{"o":[{"a":[{"n":[{"t":[{"i":[{"g":[{"e":[{"n":[{},[0]]},[0]]},[0]]},[0]]},[0]]},[0]]},[0]]},[0]],"u":[{"r":[{"o":[{"f":[{"i":[{"b":[{"r":[{"o":[{"m":[{"a":[{"t":[{"o":[{"s":[{"i":[{"s":[{},[1]]},[1]]},[1]]},[1]]},[1]]},[1]]},[1]]},[1]]},[1]]},[1]]},[1]]},[1]],"b":[{"l":[{"a":[{"s":[{"t":[{"o":[{"m":[{"a":[{},[5]]},[5]]},[5]]},[5]]},[5]]},[5]]},[5]]},[5]],"n":[{"a":[{"l":[{},[23]]},[23]]},[23]]},[1,5,23]],"a":[{"l":[{},[19,26,29]]},[19,26,29]]},[1,5,19,23,26,29]]},[1,5,19,23,26,29]],"a":[{"g":[{"e":[{},[2,21]]},[2,21]]},[2,21]],"s":[{"s":[{},[16,19]],"i":[{"s":[{},[30]]},[30]]},[16,19,20,30]],"d":[{},[18]]},[0,1,2,4,5,6,7,8,14,16,18,19,20,21,23,24,25,26,29,30]],"t":[{"i":[{"g":[{"e":[{"n":[{},[0]]},[0]]},[0]],"f":[{"i":[{"e":[{"s":[{},[0,5]]},[0,5]]},[0,5]]},[0,5]],"a":[{"t":[{"i":[{"o":[{"n":[{":":[{},[15]]},[11,15,23,26]]},[11,15,23,26]]},[11,15,23,26]]},[11,15,23,26]],"l":[{},[23]]},[11,15,23,26]]},[0,5,11,15,23,26]],"s":[{},[1,4]],"e":[{"n":[{"a":[{"n":[{"c":[{"e":[{},[9]]},[9]]},[9]]},[9]]},[9]]},[9]],"a":[{"i":[{"n":[{"e":[{"d":[{},[18]]},[18]]},[18]]},[18]]},[18]],"r":[{"o":[{"l":[{"s":[{},[26]]},[26,27]]},[26,27]]},[26,27]]},[0,1,3,4,5,9,11,12,15,17,18,21,23,26,27,30]],"d":[{"s":[{"c":[{"a":[{"p":[{"e":[{},[1]]},[1]]},[1]]},[1]]},[1]],"e":[{"r":[{},[10]],"n":[{"t":[{},[12]]},[12]]},[10,12]]},[0,1,6,7,9,10,11,12,13,14,15,16,19,20,22,23,25,26,28,29,30,32]],"f":[{"i":[{"l":[{"t":[{"r":[{"a":[{"t":[{"e":[{"s":[{},[0]]},[0]]},[0]]},[0]]},[0]]},[0]]},[0]]},[0]],"o":[{"r":[{"c":[{"i":[{"n":[{"g":[{},[4]]},[4]]},[4]],"e":[{"s":[{},[11]]},[11]]},[4,11]]},[4,11]]},[4,11]]},[0,4,11]],"g":[{"e":[{"s":[{"t":[{},[0]]},[0]]},[0]],"l":[{"e":[{"-":[{"c":[{"e":[{"l":[{"l":[{},[2]]},[2]]},[2]]},[2]]},[2]]},[2]]},[2]],"i":[{"o":[{"g":[{"e":[{"n":[{"e":[{"s":[{"i":[{"s":[{},[30]]},[30]]},[30]]},[30]]},[30]]},[30]]},[30]]},[30]]},[30]]},[0,2,4,6,15,17,20,23,26,28,30,31,32]],"s":[{"c":[{"r":[{"i":[{"p":[{"t":[{"o":[{"m":[{"e":[{},[2]]},[2]]},[2]],"i":[{"o":[{"n":[{"a":[{"l":[{},[22]]},[22]]},[4,21,22]]},[4,21,22]]},[4,21,22]]},[2,4,21,22]]},[2,4,21,22]]},[2,4,21,22]]},[2,4,21,22]]},[2,4,21,22]],"o":[{"n":[{},[6]]},[6]],"f":[{"o":[{"r":[{"m":[{"a":[{"t":[{"i":[{"o":[{"n":[{},[7,17]]},[7,17]]},[7,17]]},[7,17]]},[7,17]],"i":[{"n":[{"g":[{},[20]]},[20]]},[20]]},[7,17,20]]},[7,17,20]]},[7,17,20]]},[7,17,20]],"i":[{"v":[{"e":[{},[14]]},[14]]},[14]],"t":[{},[15]],":":[{},[16]]},[2,4,6,7,8,13,14,15,16,17,19,20,21,22,29,32]],"k":[{},[4]],"i":[{"t":[{"o":[{"b":[{"a":[{"-":[{"j":[{"o":[{"h":[{"n":[{"s":[{"o":[{"n":[{},[6]]},[6]]},[6]]},[6]]},[6]]},[6]]},[6]]},[6]]},[6]]},[6]]},[6]],"i":[{"a":[{"t":[{"i":[{"o":[{"n":[{",":[{},[30]]},[30]]},[30]]},[30]]},[30]]},[30]],"v":[{"e":[{},[31]]},[31]]},[30,31]]},[6,30,31]],"s":[{"m":[{},[12]]},[12]],"z":[{"e":[{},[19,23]]},[19,23]],"c":[{"h":[{"e":[{},[19]]},[19]]},[19]]},[6,12,19,23,30,31]],"o":[{"t":[{"t":[{"a":[{},[6]]},[6]],"a":[{"t":[{"i":[{"o":[{"n":[{},[14]]},[14]]},[14]]},[14]]},[14]]},[6,14]],"r":[{"m":[{"a":[{"l":[{},[7]]},[7]]},[7]]},[7]],"b":[{"l":[{"a":[{"s":[{"t":[{"o":[{"m":[{"a":[{},[31,32]]},[31,32]]},[31,32]]},[31,32]]},[31,32]]},[31,32]]},[31,32]]},[31,32]]},[6,7,14,24,25,31,32]],"c":[{"e":[{"r":[{},[12,14,16]]},[9,12,14,16]],"h":[{"y":[{"m":[{"a":[{"l":[{},[17,18]]},[17,18]]},[17,18]]},[17,18]],"r":[{"o":[{"n":[{"i":[{"z":[{"e":[{},[19,23]]},[19,23]]},[19,23]]},[19,23]]},[19,23]]},[19,23]],"o":[{"r":[{"a":[{"g":[{"e":[{},[19]]},[19]]},[19]]},[19]]},[19]]},[17,18,19,23]],"o":[{"p":[{"r":[{"o":[{"t":[{"e":[{"i":[{"n":[{"s":[{},[32]]},[26,32]]},[26,32]]},[26,32]]},[26,32]]},[26,32]]},[26,32]]},[26,32]]},[26,32]]},[9,12,14,16,17,18,19,23,26,32]],"h":[{"i":[{"b":[{"i":[{"t":[{"s":[{},[11]],"i":[{"o":[{"n":[{},[13]]},[13]]},[13]]},[11,13]]},[11,13]]},[11,13]]},[11,13]]},[11,13]],",":[{},[13,30]],"n":[{"o":[{"t":[{"a":[{"t":[{"i":[{"o":[{"n":[{},[14]]},[14]]},[14]]},[14]]},[14]]},[14]]},[14]]},[14]],":":[{},[15]],"v":[{"a":[{"s":[{"i":[{"o":[{"n":[{},[22]]},[22]]},[22]]},[22]]},[22]],"e":[{"r":[{"g":[{"e":[{},[29]]},[29]]},[29]]},[29]]},[22,29]],"‐":[{"m":[{"y":[{"c":[{"o":[{"n":[{"c":[{"o":[{"p":[{"r":[{"o":[{"t":[{"e":[{"i":[{"n":[{},[26]]},[26]]},[26]]},[26]]},[26]]},[26]]},[26]]},[26]]},[26]]},[26]]},[26]]},[26]]},[26]]},[26]]},[26]]},[]],"a":[{"t":[{"i":[{"o":[{"n":[{",":[{},[13,30]],":":[{},[15]]},[0,3,7,11,12,13,14,15,17,22,23,26,28,30]]},[0,3,7,11,12,13,14,15,17,22,23,26,28,30]],"e":[{"n":[{"t":[{"s":[{},[1]]},[1]]},[1]]},[1]]},[0,1,3,7,11,12,13,14,15,17,22,23,26,28,30]],"e":[{"s":[{},[0,9,30,32]]},[0,9,29,30,32]],"o":[{"s":[{"i":[{"s":[{},[1]]},[1]]},[1]],"r":[{"y":[{},[5]],"s":[{},[16]]},[5,16]],"p":[{"o":[{"i":[{"e":[{"t":[{"i":[{"c":[{},[9]]},[9]]},[9]]},[9]]},[9]]},[9]]},[9]]},[1,5,9,16]],"t":[{"i":[{"n":[{"i":[{},[6]]},[6]]},[6]]},[6]]},[0,1,3,5,6,7,9,11,12,13,14,15,16,17,22,23,26,28,29,30,32]],"n":[{"t":[{"i":[{"g":[{"e":[{"n":[{},[0]]},[0]]},[0]]},[0]]},[0,17,30]],"d":[{"s":[{"c":[{"a":[{"p":[{"e":[{},[1]]},[1]]},[1]]},[1]]},[1]]},[0,1,6,7,9,11,13,14,15,16,19,20,22,23,25,26,28,29,30,32]],"s":[{"c":[{"r":[{"i":[{"p":[{"t":[{"o":[{"m":[{"e":[{},[2]]},[2]]},[2]],"i":[{"o":[{"n":[{"a":[{"l":[{},[22]]},[22]]},[4,21,22]]},[4,21,22]]},[4,21,22]]},[2,4,21,22]]},[2,4,21,22]]},[2,4,21,22]]},[2,4,21,22]]},[2,4,21,22]],"o":[{"n":[{},[6]]},[6]],"f":[{"o":[{"r":[{"m":[{"a":[{"t":[{"i":[{"o":[{"n":[{},[7,17]]},[7,17]]},[7,17]]},[7,17]]},[7,17]],"i":[{"n":[{"g":[{},[20]]},[20]]},[20]]},[7,17,20]]},[7,17,20]]},[7,17,20]]},[7,17,20]]},[2,4,6,7,17,20,21,22]],"a":[{"l":[{"y":[{"s":[{"i":[{"s":[{},[2,5]]},[2,5]]},[2,5]]},[2,5]]},[2,5]],"p":[{"h":[{"a":[{"s":[{"e":[{},[28]]},[28]]},[28]]},[28]]},[28]]},[2,5,28]],"o":[{},[6,24,25]],"g":[{"i":[{"o":[{"g":[{"e":[{"n":[{"e":[{"s":[{"i":[{"s":[{},[30]]},[30]]},[30]]},[30]]},[30]]},[30]]},[30]]},[30]]},[30]]},[6,30]],"c":[{"e":[{"r":[{},[12,14,16]]},[9,12,14,16]],"h":[{"o":[{"r":[{"a":[{"g":[{"e":[{},[19]]},[19]]},[19]]},[19]]},[19]]},[19]]},[9,12,14,16,19]],"i":[{"s":[{"m":[{},[12]]},[12]]},[12]],"n":[{"o":[{"t":[{"a":[{"t":[{"i":[{"o":[{"n":[{},[14]]},[14]]},[14]]},[14]]},[14]]},[14]]},[14]]},[14]]},[0,1,2,4,5,6,7,8,9,11,12,13,14,15,16,17,19,20,21,22,23,24,25,26,28,29,30,32]],"l":[{"i":[{"t":[{"y":[{},[0]]},[0]],"g":[{"n":[{"a":[{"n":[{"t":[{},[17]]},[17]]},[17]]},[17]]},[17]],"f":[{"a":[{"n":[{"o":[{},[24,25]]},[24,25]]},[24,25]]},[24,25]]},[0,17,24,25]],"y":[{"s":[{"i":[{"s":[{},[2,5]]},[2,5]]},[2,5]]},[2,5]],"l":[{"m":[{"a":[{"r":[{"k":[{},[3]]},[3]]},[3]]},[3]],"i":[{"n":[{"g":[{},[32]]},[32]]},[32]]},[3,6,32]],"a":[{},[6]],"d":[{"a":[{"p":[{"e":[{},[24,25]]},[24,25]]},[24,25]]},[24,25]]},[0,2,3,5,6,7,10,17,18,19,22,23,24,25,26,28,29,31,32]],"s":[{"t":[{"o":[{"m":[{"a":[{"s":[{},[0]]},[0,5,10,20,31,32]]},[0,5,10,20,31,32]]},[0,5,10,20,31,32]],"a":[{"n":[{"o":[{},[6]]},[6]]},[6]],"e":[{"r":[{},[16]]},[16]]},[0,5,6,10,16,20,31,32]],"o":[{"r":[{"e":[{"l":[{"l":[{"a":[{},[6,24,25]]},[6,24,25]]},[6,24,25]]},[6,24,25]]},[6,24,25]]},[6,24,25]],"c":[{"a":[{"d":[{"e":[{},[7]]},[7]]},[7]]},[7]],"e":[{},[9,23,26,28]],"u":[{"s":[{":":[{},[14]]},[14]]},[14]],"i":[{"o":[{"n":[{},[22]]},[22]]},[22]]},[0,3,5,6,7,9,10,14,16,20,22,23,24,25,26,28,31,32]],"r":[{"k":[{},[3]],"o":[{"f":[{"a":[{"n":[{"o":[{},[6]]},[6]]},[6]]},[6]],"n":[{"e":[{},[6,24,25]]},[6,24,25]]},[6,24,25]],"i":[{"a":[{"n":[{},[7]]},[7]]},[6,7]],"e":[{"l":[{"l":[{"i":[{},[6]]},[6]]},[6]]},[6,21]],"a":[{"c":[{"t":[{"e":[{"r":[{"i":[{"z":[{"a":[{"t":[{"i":[{"o":[{"n":[{",":[{},[13]]},[13]]},[13]]},[13]]},[13]]},[13]]},[13]]},[13]]},[13]]},[13]]},[13]]},[13]]},[13]],"g":[{"e":[{"t":[{},[32]]},[32]]},[32]]},[1,3,6,7,13,21,24,25,32]],"p":[{"1":[{},[18]],"e":[{},[1,24,25]],"y":[{},[10]],"h":[{"o":[{"r":[{"i":[{"n":[{},[22]]},[22]]},[22]]},[22]],"a":[{"s":[{"e":[{},[28]]},[28]]},[28]]},[22,28]]},[1,10,18,22,24,25,28]],"g":[{"e":[{"s":[{},[31]]},[2,19,21,31]],"n":[{"o":[{"t":[{"t":[{"a":[{},[6]]},[6]]},[6]]},[6]]},[6]],"a":[{"i":[{"n":[{"s":[{"t":[{},[15]]},[15]]},[15]]},[15]]},[15]],"g":[{"r":[{"e":[{"s":[{"s":[{"i":[{"v":[{"e":[{"n":[{"e":[{"s":[{"s":[{},[16]]},[16]]},[16]]},[16]]},[16]]},[16]]},[16]]},[16]]},[16]]},[16]]},[16]]},[16]]},[2,6,15,16,19,21,31]],"d":[{"2":[{},[27]],"4":[{"-":[{"m":[{"y":[{"c":[{"n":[{},[5]]},[5]]},[5]]},[5]]},[5]]},[5]],"e":[{},[2,7,18]],"a":[{"t":[{"i":[{"o":[{"n":[{},[28]]},[28]]},[28]]},[28]]},[28]]},[2,5,7,18,27,28]],"c":[{"t":[{"o":[{"r":[{"s":[{},[21]]},[4,21]]},[4,21]],"i":[{"v":[{"a":[{"t":[{"i":[{"o":[{"n":[{},[12,17]]},[12,17]]},[12,17]]},[12,17]]},[12,17]]},[12,17]]},[12,17]],"e":[{"r":[{"i":[{"z":[{"a":[{"t":[{"i":[{"o":[{"n":[{",":[{},[13]]},[13]]},[13]]},[13]]},[13]]},[13]]},[13]]},[13]]},[13]]},[13]]},[4,12,13,17,21]],"k":[{},[5]],"c":[{},[8,13,20]],"r":[{"o":[{"p":[{"h":[{"a":[{"g":[{"e":[{"s":[{},[31]]},[31]]},[31]]},[31]]},[31]]},[31]]},[31]]},[31]]},[4,5,8,12,13,17,20,21,31]],"ï":[{"v":[{"e":[{},[4]]},[4]]},[4]],"m":[{",":[{},[6]]},[4,6]],",":[{},[6,24,25]],"-":[{"j":[{"o":[{"h":[{"n":[{"s":[{"o":[{"n":[{},[6]]},[6]]},[6]]},[6]]},[6]]},[6]]},[6]]},[6]],"v":[{"a":[{"r":[{"o":[{"n":[{"e":[{},[6,24,25]]},[6,24,25]]},[6,24,25]]},[6,24,25]]},[6,24,25]]},[6,24,25]],"i":[{"n":[{"s":[{"t":[{},[15]]},[7,15]],"t":[{"e":[{"n":[{"a":[{"n":[{"c":[{"e":[{},[9]]},[9]]},[9]]},[9]]},[9]]},[9]],"a":[{"i":[{"n":[{"e":[{"d":[{},[18]]},[18]]},[18]]},[18]]},[18]]},[9,18]],"e":[{"d":[{},[18]]},[18]]},[7,9,15,18,26]]},[7,9,15,18,26]],"x":[{"i":[{"s":[{},[18,27]]},[18,27]],"o":[{"n":[{"a":[{"l":[{},[28]]},[28]]},[28]]},[28]]},[18,27,28]],"b":[{"i":[{"l":[{"i":[{"z":[{"i":[{"n":[{"g":[{},[26]]},[26]]},[26]]},[26]],"t":[{"y":[{},[27]]},[27]]},[26,27]]},[26,27]]},[26,27]]},[26,27]],"‐":[{"t":[{"r":[{"c":[{"p":[{"‐":[{"r":[{"e":[{"s":[{"t":[{"‐":[{"m":[{"a":[{"d":[{"2":[{},[27]]},[27]]},[27]]},[27]]},[27]]},[27]]},[27]]},[27]]},[27]]},[27]]},[27]]},[27]]},[27]]},[27]]},[27]]},[]],"f":[{"i":[{"l":[{"t":[{"r":[{"a":[{"t":[{"e":[{"s":[{},[0]]},[0]]},[0]]},[0]]},[0]]},[0]]},[0]],"e":[{"s":[{},[0,5]]},[0,5]],"b":[{"r":[{"o":[{"m":[{"a":[{"t":[{"o":[{"s":[{"i":[{"s":[{},[1]]},[1]]},[1]]},[1]]},[1]]},[1]]},[1]]},[1]]},[1]]},[1]],"n":[{"i":[{"t":[{"i":[{"v":[{"e":[{},[31]]},[31]]},[31]]},[31]]},[31]]},[31]]},[0,1,5,31]],"a":[{"c":[{"t":[{"o":[{"r":[{"s":[{},[21]]},[4,21]]},[4,21]]},[4,21]]},[4,21]],"n":[{"o":[{},[6,24,25]]},[6,24,25]]},[4,6,21,24,25]],"r":[{"o":[{"m":[{},[4]]},[4]],"a":[{"t":[{"t":[{"i":[{"n":[{"i":[{},[6]]},[6]]},[6]]},[6]]},[6]]},[6]],"e":[{"d":[{"e":[{"r":[{"i":[{"c":[{"k":[{},[6]]},[6]]},[6]]},[6]]},[6]]},[6]]},[6]],"-":[{"t":[{"a":[{"c":[{"c":[{},[8,13]]},[8,13]]},[8,13]]},[8,13]]},[8,13]]},[4,6,8,13,20]],"o":[{"r":[{"c":[{"i":[{"n":[{"g":[{},[4]]},[4]]},[4]],"e":[{"s":[{},[11]]},[11]]},[4,11]],"m":[{"a":[{"t":[{"i":[{"o":[{"n":[{},[7,17]]},[7,17]]},[7,17]]},[7,17]]},[7,17]],"i":[{"n":[{"g":[{},[20]]},[20]]},[20]]},[7,17,20]]},[4,7,11,12,14,17,20,21]]},[4,7,11,12,14,17,20,21]],"e":[{"e":[{"d":[{"b":[{"a":[{"c":[{"k":[{},[5]]},[5]]},[5]]},[5]]},[5]]},[5]],"r":[{"e":[{"n":[{"t":[{"i":[{"a":[{"t":[{"i":[{"o":[{"n":[{":":[{},[15]]},[11,15,23,26]]},[11,15,23,26]]},[11,15,23,26]]},[11,15,23,26]]},[11,15,23,26]]},[11,15,23,26]]},[11,15,23,26]]},[11,15,23,26]]},[11,15,23,26]],"a":[{"t":[{"i":[{"o":[{"n":[{},[26,30]]},[26,30]]},[26,30]]},[26,30]]},[26,30]]},[11,15,23,26,30]],"t":[{"a":[{"l":[{},[31]]},[31]]},[31]]},[5,11,15,23,26,30,31]],"g":[{"f":[{"r":[{"-":[{"t":[{"a":[{"c":[{"c":[{},[8,13]]},[8,13]]},[8,13]]},[8,13]]},[8,13]]},[8,13,20]]},[8,13,20]]},[8,13,20]],"u":[{"s":[{"i":[{"o":[{"n":[{"s":[{},[8,13,14,20]]},[8,13,14,20]]},[8,13,14,20]]},[8,13,14,20]]},[8,13,14,20]]},[8,13,14,20]],"f":[{"e":[{"r":[{"e":[{"n":[{"t":[{"i":[{"a":[{"t":[{"i":[{"o":[{"n":[{":":[{},[15]]},[11,15,23,26]]},[11,15,23,26]]},[11,15,23,26]]},[11,15,23,26]]},[11,15,23,26]]},[11,15,23,26]]},[11,15,23,26]]},[11,15,23,26]]},[11,15,23,26]]},[11,15,23,26]]},[11,15,23,26]]},[11,15,23,26]],"h":[{},[11]],",":[{},[24,25]]},[]],"g":[{"e":[{"n":[{"e":[{"s":[{"i":[{"s":[{},[30]]},[30]]},[20,30]]},[4,8,14,20,30]]},[0,4,8,14,20,30]],"s":[{"t":[{},[0]]},[0,31]],"r":[{"i":[{"n":[{"g":[{},[17]]},[17]]},[17]]},[17]],"t":[{},[32]]},[0,2,4,8,14,17,19,20,21,29,30,31,32]],"l":[{"i":[{"o":[{"b":[{"l":[{"a":[{"s":[{"t":[{"o":[{"m":[{"a":[{"s":[{},[0]]},[0,10,20]]},[0,10,20]]},[0,10,20]]},[0,10,20]]},[0,10,20]]},[0,10,20]]},[0,10,20]]},[0,10,20]],"m":[{"a":[{"s":[{},[3]]},[1,2,3,8,13,17,18]]},[1,2,3,8,13,17,18]]},[0,1,2,3,8,10,13,17,18,20]],"a":[{"l":[{},[23]]},[23]]},[0,1,2,3,8,10,13,17,18,20,23]],"e":[{"-":[{"c":[{"e":[{"l":[{"l":[{},[2]]},[2]]},[2]]},[2]]},[2]]},[2]]},[0,1,2,3,8,10,13,17,18,20,23]],"h":[{"-":[{"g":[{"r":[{"a":[{"d":[{"e":[{},[2,18]]},[2,18]]},[2,18]]},[2,18]]},[2,18]],"r":[{"i":[{"s":[{"k":[{},[5]]},[5]]},[5]]},[5]]},[2,5,18]]},[2,5,7,18,22]],"r":[{"a":[{"d":[{"e":[{},[2,18]],"a":[{"t":[{"i":[{"o":[{"n":[{},[28]]},[28]]},[28]]},[28]]},[28]]},[2,18,28]],"m":[{},[4]],"t":[{"i":[{"o":[{"n":[{},[22]]},[22]]},[22]]},[22]]},[2,4,18,22,28]],"o":[{"w":[{"t":[{"h":[{},[7,28]]},[7,28]]},[7,28]]},[7,28]],"e":[{"s":[{"s":[{"i":[{"v":[{"e":[{"n":[{"e":[{"s":[{"s":[{},[16]]},[16]]},[16]]},[16]]},[16]]},[16]]},[16]]},[16]]},[16]]},[16]]},[2,4,7,16,18,22,28]],"u":[{"l":[{"a":[{"t":[{"o":[{"r":[{"y":[{},[5]],"s":[{},[16]]},[5,16]]},[5,16]],"e":[{"s":[{},[9]]},[9,29]]},[5,9,16,29]]},[5,9,16,29]]},[5,9,16,29]],"i":[{"l":[{"l":[{"e":[{"m":[{"o":[{"t":[{},[25]]},[25]]},[25]]},[25]]},[25]]},[25]]},[25]]},[5,9,16,25,29]],"n":[{"o":[{"t":[{"t":[{"a":[{},[6]]},[6]]},[6]]},[6]],"a":[{"n":[{"t":[{},[17]]},[17]],"l":[{"l":[{"i":[{"n":[{"g":[{},[32]]},[32]]},[32]]},[32]]},[32]]},[17,32]]},[6,17,32]],"a":[{"r":[{"o":[{"f":[{"a":[{"n":[{"o":[{},[6]]},[6]]},[6]]},[6]]},[6]]},[6]],"s":[{"e":[{},[9,23,26]],"u":[{"s":[{":":[{},[14]]},[14]]},[14]]},[9,14,23,26]],"i":[{"n":[{"s":[{"t":[{},[15]]},[15]]},[15]]},[15]]},[6,9,14,15,23,26]],",":[{},[6]],"f":[{"r":[{"-":[{"t":[{"a":[{"c":[{"c":[{},[8,13]]},[8,13]]},[8,13]]},[8,13]]},[8,13]]},[8,13,20]]},[8,13,20]],"o":[{"i":[{"n":[{"g":[{},[15]]},[15]]},[15]]},[15]],"g":[{"r":[{"e":[{"s":[{"s":[{"i":[{"v":[{"e":[{"n":[{"e":[{"s":[{"s":[{},[16]]},[16]]},[16]]},[16]]},[16]]},[16]]},[16]]},[16]]},[16]]},[16]]},[16]],"e":[{"r":[{"i":[{"n":[{"g":[{},[17]]},[17]]},[17]]},[17]]},[17]]},[16,17]],"i":[{"o":[{"g":[{"e":[{"n":[{"e":[{"s":[{"i":[{"s":[{},[30]]},[30]]},[30]]},[30]]},[30]]},[30]]},[30]]},[30]]},[30]]},[]],"q":[{"u":[{"a":[{"l":[{"i":[{"t":[{"y":[{},[0]]},[0]]},[0]]},[0]]},[0]],"i":[{"t":[{"i":[{"n":[{},[9,23,26]]},[9,23,26]]},[9,23,26]],"r":[{"e":[{"d":[{},[21]]},[21]]},[21]]},[9,21,23,26]]},[0,9,21,23,26]]},[]],"u":[{"a":[{"l":[{"i":[{"t":[{"y":[{},[0]]},[0]]},[0]]},[0]],"n":[{"g":[{},[6]]},[6]]},[0,6]],"r":[{"v":[{"i":[{"v":[{"a":[{"l":[{},[0]]},[0]]},[0]]},[0]]},[0]],"o":[{"f":[{"i":[{"b":[{"r":[{"o":[{"m":[{"a":[{"t":[{"o":[{"s":[{"i":[{"s":[{},[1]]},[1]]},[1]]},[1]]},[1]]},[1]]},[1]]},[1]]},[1]]},[1]]},[1]]},[1]],"b":[{"l":[{"a":[{"s":[{"t":[{"o":[{"m":[{"a":[{},[5]]},[5]]},[5]]},[5]]},[5]]},[5]]},[5]]},[5]],"n":[{"a":[{"l":[{},[23]]},[23]]},[23]]},[1,5,23]],"r":[{"e":[{"n":[{"t":[{},[3,15]]},[3,15]]},[3,15]]},[3,15]],"i":[{"n":[{"g":[{},[4]]},[4]]},[4]],"a":[{"l":[{},[19,26,29]]},[19,26,29]]},[0,1,3,4,5,15,16,19,23,26,29]],"l":[{"a":[{"r":[{},[1]],"t":[{"o":[{"r":[{"y":[{},[5]],"s":[{},[16]]},[5,16]]},[5,16]],"e":[{"s":[{},[9]]},[9,29]]},[5,9,16,29]]},[1,5,9,16,29]],"o":[{},[6]]},[1,5,6,9,16,29]],"t":[{"a":[{"t":[{"i":[{"o":[{"n":[{},[3]]},[3]]},[3]]},[3]],"n":[{"t":[{},[30]]},[30]]},[3,30]],"i":[{"o":[{"n":[{},[10]]},[10]]},[10]]},[3,10,30]],"s":[{"s":[{"o":[{},[6]]},[6]],"t":[{"a":[{"i":[{"n":[{"s":[{},[7]]},[7]]},[7]]},[7]]},[7]],"i":[{"o":[{"n":[{"s":[{},[8,13,14,20]]},[8,13,14,20]]},[8,13,14,20]]},[8,13,14,20]],":":[{},[14]]},[6,7,8,13,14,20]],"w":[{"e":[{"1":[{},[7,9,23,26]]},[7,9,23,26]]},[7,9,23,26]],"m":[{"o":[{"r":[{},[7,22,30]],"u":[{"r":[{},[16]]},[16]]},[7,16,22,30]],"a":[{"n":[{},[8,20]]},[8,20]]},[7,8,16,20,22,23,30]],"g":[{"h":[{},[7,22]]},[7,22]],"b":[{"i":[{"q":[{"u":[{"i":[{"t":[{"i":[{"n":[{},[9,23,26]]},[9,23,26]]},[9,23,26]]},[9,23,26]]},[9,23,26]]},[9,23,26]]},[9,23,26]]},[9,23,26]],"i":[{"t":[{"i":[{"n":[{},[9,23,26]]},[9,23,26]]},[9,23,26]],"r":[{"e":[{"d":[{},[21]]},[21]]},[21]],"l":[{"l":[{"e":[{"m":[{"o":[{"t":[{},[25]]},[25]]},[25]]},[25]]},[25]]},[25]]},[9,21,23,25,26]],"n":[{"d":[{"e":[{"r":[{},[10]]},[10]]},[10]]},[10]],"d":[{"w":[{"i":[{"g":[{},[25]]},[25]]},[25]]},[25]],"p":[{"l":[{"e":[{"s":[{},[28]]},[28]]},[28]]},[28]]},[]],"l":[{"i":[{"t":[{"y":[{},[0,27]]},[0,27]],"o":[{"b":[{"l":[{"a":[{"s":[{"t":[{"o":[{"m":[{"a":[{"s":[{},[0]]},[0,10,20]]},[0,10,20]]},[0,10,20]]},[0,10,20]]},[0,10,20]]},[0,10,20]]},[0,10,20]]},[0,10,20]],"m":[{"a":[{"s":[{},[3]]},[1,2,3,8,13,17,18]]},[1,2,3,8,13,17,18]]},[0,1,2,3,8,10,13,17,18,20]],"n":[{"e":[{"a":[{"g":[{"e":[{},[2,21]]},[2,21]]},[2,21]]},[2,21]],"g":[{},[32]]},[2,21,32]],"a":[{"l":[{},[7,23]]},[7,23]],"g":[{"a":[{"s":[{"e":[{},[9,23,26]]},[9,23,26]]},[9,23,26]],"n":[{"a":[{"n":[{"t":[{},[17]]},[17]]},[17]]},[17]]},[9,17,23,26]],"f":[{"a":[{"n":[{"o":[{},[24,25]]},[24,25]]},[24,25]],"e":[{"r":[{"a":[{"t":[{"i":[{"o":[{"n":[{},[26,30]]},[26,30]]},[26,30]]},[26,30]]},[26,30]]},[26,30]]},[26,30]]},[24,25,26,30]],"z":[{"i":[{"n":[{"g":[{},[26]]},[26]]},[26]]},[26]],"v":[{"e":[{"r":[{},[31]]},[31]]},[31]]},[0,1,2,3,6,7,8,9,10,13,17,18,20,21,23,24,25,26,27,30,31,32]],"y":[{"m":[{"p":[{"h":[{"o":[{"c":[{"y":[{"t":[{"e":[{},[0,4]]},[0,4]]},[0,4]]},[0,4]],"i":[{"d":[{},[9]]},[9]]},[0,4,9]]},[0,4,9]]},[0,4,9]]},[0,4,9]],"s":[{"i":[{"s":[{},[2,5]]},[2,5]]},[2,5]]},[0,2,4,5,9]],"t":[{"r":[{"a":[{"t":[{"e":[{"s":[{},[0]]},[0]]},[0]]},[0]]},[0]]},[0]],"a":[{"s":[{"t":[{"o":[{"m":[{"a":[{"s":[{},[0]]},[0,5,10,20,31,32]]},[0,5,10,20,31,32]]},[0,5,10,20,31,32]]},[0,5,10,20,31,32]],"o":[{"r":[{"e":[{"l":[{"l":[{"a":[{},[6,24,25]]},[6,24,25]]},[6,24,25]]},[6,24,25]]},[6,24,25]]},[6,24,25]]},[0,5,6,10,20,24,25,31,32]],"r":[{},[1]],"n":[{"d":[{"s":[{"c":[{"a":[{"p":[{"e":[{},[1]]},[1]]},[1]]},[1]]},[1]]},[1,6]]},[1,6]],"t":[{"o":[{"r":[{"y":[{},[5]],"s":[{},[16]]},[5,16]]},[5,16]],"e":[{"s":[{},[9]]},[9,29]]},[5,9,16,29]]},[0,1,5,6,9,10,16,20,24,25,29,31,32]],"o":[{"n":[{"g":[{"e":[{"s":[{"t":[{},[0]]},[0]]},[0]]},[0]],"a":[{"l":[{},[10]]},[10]]},[0,10]],"p":[{"m":[{"e":[{"n":[{"t":[{},[4,21]]},[4,21]]},[4,21]]},[4,21]],"i":[{"n":[{"g":[{},[23]]},[23]]},[23]]},[4,21,23]],"o":[{"p":[{},[5]]},[5]]},[0,4,5,6,10,21,23]],"e":[{"c":[{"u":[{"l":[{"a":[{"r":[{},[1]]},[1]]},[1]]},[1]]},[1]],"-":[{"c":[{"e":[{"l":[{"l":[{},[2]]},[2]]},[2]]},[2]]},[2]],"m":[{"e":[{"n":[{"t":[{},[5]]},[5]]},[5]],"o":[{"t":[{},[25]]},[25]]},[5,25]],"e":[{},[6]],"w":[{"i":[{"s":[{},[6]]},[6]]},[6]],"n":[{"i":[{"t":[{"o":[{"b":[{"a":[{"-":[{"j":[{"o":[{"h":[{"n":[{"s":[{"o":[{"n":[{},[6]]},[6]]},[6]]},[6]]},[6]]},[6]]},[6]]},[6]]},[6]]},[6]]},[6]]},[6]]},[6]]},[6]],"x":[{},[28]],"s":[{},[28]]},[1,2,5,6,25,28,29]],"l":[{"m":[{"a":[{"r":[{"k":[{},[3]]},[3]]},[3]]},[3]],"a":[{"n":[{"d":[{},[6]]},[6]]},[6,24,25]],"i":[{"n":[{"g":[{},[32]]},[32]]},[6,32]],"s":[{},[9,16,19,21,29]],"u":[{"m":[{},[23]]},[23]],"e":[{"m":[{"o":[{"t":[{},[25]]},[25]]},[25]]},[25]]},[2,3,4,6,7,9,16,19,21,22,23,24,25,28,29,32]],"m":[{"a":[{"r":[{"k":[{},[3]]},[3]],"n":[{},[24]]},[3,24]]},[3,24]],",":[{},[6,24]],"s":[{},[9,16,19,21,26,29]],"u":[{"t":[{"i":[{"o":[{"n":[{},[10]]},[10]]},[10]]},[10]],"m":[{},[23]],"d":[{"w":[{"i":[{"g":[{},[25]]},[25]]},[25]]},[25]]},[10,23,25]],"d":[{"-":[{"t":[{"y":[{"p":[{"e":[{},[13]]},[13]]},[13]]},[13]]},[13]],"a":[{"p":[{"e":[{},[24,25]]},[24,25]]},[24,25]]},[13,24,25]]},[]],"y":[{"m":[{"p":[{"h":[{"o":[{"c":[{"y":[{"t":[{"e":[{},[0,4]]},[0,4]]},[0,4]]},[0,4]],"i":[{"d":[{},[9]]},[9]]},[0,4,9]]},[0,4,9]]},[0,4,9]],"a":[{"l":[{},[17,18]]},[17,18]]},[0,4,9,17,18]],"t":[{"e":[{},[0,4]],"h":[{"r":[{"o":[{"p":[{"o":[{"i":[{"e":[{"s":[{"i":[{"s":[{},[31]]},[31]]},[31]]},[31]]},[31]]},[31]]},[31]]},[31]]},[31]]},[31]]},[0,4,31]],"s":[{"i":[{"s":[{},[2,5]]},[2,5]]},[2,5]],"c":[{"n":[{},[5]],"o":[{"n":[{"c":[{"o":[{"p":[{"r":[{"o":[{"t":[{"e":[{"i":[{"n":[{},[26]]},[26]]},[26]]},[26]]},[26]]},[26]]},[26]]},[26]]},[26]]},[26]]},[26]],"l":[{"e":[{},[28,29]]},[28,29]]},[5,15,26,28,29,32]],"p":[{"e":[{},[13]]},[13]],"n":[{"c":[{"h":[{"r":[{"o":[{"n":[{"i":[{"z":[{"e":[{},[19,23]]},[19,23]]},[19,23]]},[19,23]]},[19,23]]},[19,23]]},[19,23]]},[19,23]]},[19,23]]},[]],"d":[{"2":[{"-":[{"d":[{"e":[{"p":[{"e":[{"n":[{"d":[{"e":[{"n":[{"t":[{},[12]]},[12]]},[12]]},[12]]},[12]]},[12]]},[12]]},[12]]},[12]]},[12]]},[4,11,12,22,27,28,29,30,31,32]],"4":[{"-":[{"m":[{"y":[{"c":[{"n":[{},[5]]},[5]]},[5]]},[5]]},[5]],"(":[{"+":[{")":[{},[21]]},[21]]},[21]]},[5,21]],"e":[{"n":[{"t":[{"i":[{"f":[{"i":[{"e":[{"s":[{},[0,5]]},[0,5]]},[0,5]]},[0,5]]},[0,5]]},[0,5,12]]},[0,5,12]],"v":[{"e":[{"l":[{"o":[{"p":[{"m":[{"e":[{"n":[{"t":[{},[4,21]]},[4,21]]},[4,21]]},[4,21]],"i":[{"n":[{"g":[{},[23]]},[23]]},[23]]},[4,21,23]]},[4,21,23]]},[4,21,23]]},[4,21,23]]},[4,21,23]],"r":[{"i":[{"c":[{"k":[{},[6]]},[6]]},[6]]},[6,10]],"p":[{"e":[{"n":[{"d":[{"e":[{"n":[{"t":[{},[12]]},[12]]},[12]]},[12]]},[12]]},[12]]},[12]],"t":[{"e":[{"c":[{"t":[{"i":[{"o":[{"n":[{",":[{},[13]]},[13,14]]},[13,14]]},[13,14]]},[13,14]]},[13,14]]},[13,14]]},[13,14]],"s":[{"t":[{"a":[{"b":[{"i":[{"l":[{"i":[{"z":[{"i":[{"n":[{"g":[{},[26]]},[26]]},[26]]},[26]]},[26]]},[26]]},[26]]},[26]]},[26]]},[26]]},[26]],"g":[{"r":[{"a":[{"d":[{"a":[{"t":[{"i":[{"o":[{"n":[{},[28]]},[28]]},[28]]},[28]]},[28]]},[28]]},[28]]},[28]]},[28]],"f":[{"i":[{"n":[{"i":[{"t":[{"i":[{"v":[{"e":[{},[31]]},[31]]},[31]]},[31]]},[31]]},[31]]},[31]]},[31]]},[0,2,4,5,6,7,10,12,13,14,18,21,23,26,28,31]],"s":[{"c":[{"a":[{"p":[{"e":[{},[1]]},[1]]},[1]]},[1]]},[1]],"i":[{"v":[{"e":[{"r":[{"s":[{"i":[{"t":[{"y":[{},[2]]},[2]]},[2]]},[2]]},[2]]},[2]]},[2]],"f":[{"f":[{"e":[{"r":[{"e":[{"n":[{"t":[{"i":[{"a":[{"t":[{"i":[{"o":[{"n":[{":":[{},[15]]},[11,15,23,26]]},[11,15,23,26]]},[11,15,23,26]]},[11,15,23,26]]},[11,15,23,26]]},[11,15,23,26]]},[11,15,23,26]]},[11,15,23,26]]},[11,15,23,26]]},[11,15,23,26]]},[11,15,23,26]]},[11,15,23,26]]},[11,15,23,26]],"c":[{"t":[{"i":[{"o":[{"n":[{},[14]]},[14]]},[14]]},[14]]},[14]],"a":[{"t":[{"e":[{"s":[{},[30,32]]},[30,32]]},[30,32]]},[30,32]]},[2,11,14,15,23,26,30,32]],"o":[{"i":[{"d":[{},[3]]},[3]],"e":[{"t":[{"s":[{"c":[{"h":[{},[24]]},[24]]},[24]]},[24]]},[24]],"m":[{"a":[{"i":[{"n":[{},[26]]},[26]]},[26]]},[26]]},[3,24,26]],"u":[{"r":[{"i":[{"n":[{"g":[{},[4]]},[4]]},[4]]},[4]]},[4]],"b":[{"a":[{"c":[{"k":[{},[5]]},[5]]},[5]]},[5]],"c":[{"m":[{",":[{},[6]]},[6]]},[6]],"h":[{},[13]],"-":[{"t":[{"y":[{"p":[{"e":[{},[13]]},[13]]},[13]]},[13]],"r":[{"a":[{"p":[{"1":[{},[18]]},[18]]},[18]]},[18]]},[13,18]],"r":[{"i":[{"v":[{"e":[{"r":[{},[14]],"s":[{},[17]]},[14,17]]},[14,17]]},[14,17]]},[14,17]],"a":[{"p":[{"e":[{},[24,25]]},[24,25]],"t":[{"i":[{"o":[{"n":[{},[28]]},[28]]},[28]]},[28]]},[24,25,28]],"w":[{"i":[{"g":[{},[25]]},[25]]},[25]]},[]],"p":[{"1":[{},[18]],"2":[{},[29]],"5":[{"7":[{"k":[{"i":[{"p":[{"2":[{},[29]]},[29]]},[29]]},[29]]},[29]]},[29]],"h":[{"o":[{"c":[{"y":[{"t":[{"e":[{},[0,4]]},[0,4]]},[0,4]]},[0,4]],"i":[{"d":[{},[9]]},[9]],"r":[{"i":[{"n":[{},[22]]},[22]]},[22]]},[0,4,9,22]],"a":[{"s":[{"e":[{},[28]]},[28]],"g":[{"e":[{"s":[{},[31]]},[31]]},[31]]},[28,31]]},[0,4,9,22,28,31]],"e":[{"n":[{"d":[{"e":[{"n":[{"t":[{},[12]]},[12]]},[12]]},[12]]},[12]],"g":[{"a":[{"s":[{"u":[{"s":[{":":[{},[14]]},[14]]},[14]]},[14]]},[14]]},[14]]},[1,12,13,14,24,25]],"a":[{"t":[{"i":[{"e":[{"n":[{"t":[{"s":[{},[1]]},[1]]},[1]]},[1]]},[1]]},[1]],"g":[{"n":[{"o":[{"t":[{"t":[{"a":[{},[6]]},[6]]},[6]]},[6]]},[6]]},[6]]},[1,6]],"t":[{"o":[{"m":[{"e":[{},[2]]},[2]]},[2]],"i":[{"o":[{"n":[{"a":[{"l":[{},[22]]},[22]]},[4,21,22]]},[4,21,22]]},[4,21,22]]},[2,4,21,22]],"o":[{"i":[{"n":[{"t":[{},[3]]},[3]],"e":[{"t":[{"i":[{"c":[{},[9]]},[9]]},[9]],"s":[{"i":[{"s":[{},[31]]},[31]]},[31]]},[9,31]]},[3,9,31]],"s":[{"i":[{"t":[{"i":[{"v":[{"e":[{},[5]]},[5]]},[5]]},[5]]},[5]]},[5]]},[3,5,9,31]],"r":[{"k":[{"c":[{"a":[{},[3]]},[3]]},[3]],"e":[{"v":[{"e":[{"n":[{"t":[{"s":[{},[4]]},[4]]},[4]]},[4]]},[4]],"s":[{"s":[{"i":[{"o":[{"n":[{},[22]]},[22]],"n":[{"g":[{},[31]]},[31]]},[22,31]]},[11,22,31]]},[11,22,31]],"h":[{"e":[{"n":[{"s":[{"i":[{"v":[{"e":[{},[14]]},[14]]},[14]]},[14]]},[14]]},[14]]},[14]],"d":[{"i":[{"c":[{"t":[{"i":[{"o":[{"n":[{},[14]]},[14]]},[14]]},[14]]},[14]]},[14]]},[14]]},[4,11,14,22,31]],"o":[{"t":[{"e":[{"i":[{"n":[{"s":[{":":[{},[16]]},[4,16,19,29,32]]},[4,16,19,21,26,29,32]]},[4,16,19,21,26,29,32]]},[4,16,19,21,26,29,32]]},[4,16,19,21,26,29,32]],"g":[{"r":[{"a":[{"m":[{},[4]]},[4]]},[4]]},[4]],"m":[{"o":[{"t":[{"e":[{"s":[{},[22,31]]},[22,31]],"i":[{"n":[{"g":[{},[28]]},[28]]},[28]]},[22,28,31]]},[22,28,31]]},[22,28,31]],"l":[{"i":[{"f":[{"e":[{"r":[{"a":[{"t":[{"i":[{"o":[{"n":[{},[26,30]]},[26,30]]},[26,30]]},[26,30]]},[26,30]]},[26,30]]},[26,30]]},[26,30]]},[26,30]]},[26,30]]},[4,16,19,21,22,26,28,29,30,31,32]]},[3,4,11,14,16,19,21,22,26,28,29,30,31,32]],"m":[{"e":[{"n":[{"t":[{},[4,21]]},[4,21]]},[4,21]]},[4,21]],",":[{},[6]],"i":[{"t":[{"h":[{"e":[{"l":[{"i":[{"a":[{"l":[{},[7]]},[7]]},[7]]},[7]]},[7]]},[7]]},[7]],"n":[{"g":[{},[23]]},[23]]},[7,23]],"y":[{},[10]],"n":[{"2":[{},[17]]},[17]],"‐":[{"r":[{"e":[{"s":[{"t":[{"‐":[{"m":[{"a":[{"d":[{"2":[{},[27]]},[27]]},[27]]},[27]]},[27]]},[27]]},[27]]},[27]]},[27]]},[27]],"l":[{"e":[{"x":[{},[28]],"s":[{},[28]]},[28]]},[28]]},[]],"r":[{"a":[{"t":[{"e":[{"s":[{},[0]]},[0]],"t":[{"i":[{"n":[{"i":[{},[6]]},[6]]},[6]]},[6]],"i":[{"o":[{"n":[{},[22,26,30]]},[22,26,30]]},[22,26,30]]},[0,6,22,26,30]],"n":[{"s":[{"c":[{"r":[{"i":[{"p":[{"t":[{"o":[{"m":[{"e":[{},[2]]},[2]]},[2]],"i":[{"o":[{"n":[{"a":[{"l":[{},[22]]},[22]]},[4,21,22]]},[4,21,22]]},[4,21,22]]},[2,4,21,22]]},[2,4,21,22]]},[2,4,21,22]]},[2,4,21,22]]},[2,4,21,22]],"f":[{"o":[{"r":[{"m":[{"a":[{"t":[{"i":[{"o":[{"n":[{},[7,17]]},[7,17]]},[7,17]]},[7,17]]},[7,17]],"i":[{"n":[{"g":[{},[20]]},[20]]},[20]]},[7,17,20]]},[7,17,20]]},[7,17,20]]},[7,17,20]]},[2,4,7,17,20,21,22]]},[2,4,7,17,20,21,22]],"d":[{"e":[{},[2,18]],"a":[{"t":[{"i":[{"o":[{"n":[{},[28]]},[28]]},[28]]},[28]]},[28]]},[2,18,28]],"m":[{},[4]],"p":[{"1":[{},[18]],"y":[{},[10]]},[10,18]],"c":[{"t":[{"e":[{"r":[{"i":[{"z":[{"a":[{"t":[{"i":[{"o":[{"n":[{",":[{},[13]]},[13]]},[13]]},[13]]},[13]]},[13]]},[13]]},[13]]},[13]]},[13]]},[13]]},[13]],"g":[{"e":[{},[19]]},[19]],"l":[{},[19,26,29]]},[0,2,4,6,7,10,13,17,18,19,20,21,22,26,28,29,30]],"v":[{"i":[{"v":[{"a":[{"l":[{},[0]]},[0]]},[0]]},[0]]},[0]],"o":[{"f":[{"i":[{"b":[{"r":[{"o":[{"m":[{"a":[{"t":[{"o":[{"s":[{"i":[{"s":[{},[1]]},[1]]},[1]]},[1]]},[1]]},[1]]},[1]]},[1]]},[1]]},[1]]},[1]],"a":[{"n":[{"o":[{},[6]]},[6]]},[6]]},[1,6]],"m":[{"a":[{"t":[{"o":[{"s":[{"i":[{"s":[{},[1]]},[1]]},[1]]},[1]]},[1]]},[1]],"o":[{"t":[{"e":[{"s":[{},[22,31]]},[22,31]],"i":[{"n":[{"g":[{},[28]]},[28]]},[28]]},[22,28,31]],"s":[{"o":[{"m":[{"e":[{},[27]]},[27]]},[27]]},[27]]},[22,27,28,31]]},[1,4,22,27,28,31]],"t":[{"e":[{"i":[{"n":[{"s":[{":":[{},[16]]},[4,16,19,29,32]]},[4,16,19,21,26,29,32]]},[4,16,19,21,26,29,32]]},[4,16,19,21,26,29,32]]},[4,16,19,21,26,29,32]],"g":[{"r":[{"a":[{"m":[{},[4]]},[4]]},[4]]},[4]],"s":[{"s":[{"-":[{"c":[{"o":[{"h":[{"o":[{"r":[{"t":[{},[5]]},[5]]},[5]]},[5]]},[5]]},[5]]},[5]]},[5]]},[5]],"b":[{"l":[{"a":[{"s":[{"t":[{"o":[{"m":[{"a":[{},[5]]},[5]]},[5]]},[5]]},[5]]},[5]]},[5]]},[5]],"l":[{"l":[{"a":[{"n":[{"d":[{},[6]]},[6]]},[6]]},[6]],"s":[{},[26]],"i":[{"f":[{"e":[{"r":[{"a":[{"t":[{"i":[{"o":[{"n":[{},[26,30]]},[26,30]]},[26,30]]},[26,30]]},[26,30]]},[26,30]]},[26,30]]},[26,30]]},[26,30]]},[6,26,27,30]],"n":[{"e":[{},[6,24,25]],"i":[{"z":[{"e":[{},[19,23]]},[19,23]]},[19,23]],"a":[{"l":[{},[23]]},[23]]},[6,19,23,24,25]],"w":[{"t":[{"h":[{},[7,28]]},[7,28]]},[7,28]],"u":[{"g":[{"h":[{},[7,22]]},[7,22]]},[7,22]],"p":[{"o":[{"i":[{"e":[{"s":[{"i":[{"s":[{},[31]]},[31]]},[31]]},[31]]},[31]]},[31]],"h":[{"a":[{"g":[{"e":[{"s":[{},[31]]},[31]]},[31]]},[31]]},[31]]},[31]]},[1,4,5,6,7,16,19,21,22,23,24,25,26,27,28,29,30,31,32]],"i":[{"p":[{"t":[{"o":[{"m":[{"e":[{},[2]]},[2]]},[2]],"i":[{"o":[{"n":[{"a":[{"l":[{},[22]]},[22]]},[4,21,22]]},[4,21,22]]},[4,21,22]]},[2,4,21,22]]},[2,4,21,22]],"n":[{"g":[{},[4,17]]},[4,17,22]],"s":[{"k":[{},[5]]},[5]],"c":[{"k":[{},[6]]},[6]],"a":[{"n":[{},[7]]},[7]],"z":[{"a":[{"t":[{"i":[{"o":[{"n":[{",":[{},[13]]},[13]]},[13]]},[13]]},[13]]},[13]]},[13]],"v":[{"e":[{"r":[{},[14]],"s":[{},[17]]},[14,17]]},[14,17]],"g":[{"g":[{"e":[{"r":[{"i":[{"n":[{"g":[{},[17]]},[17]]},[17]]},[17]]},[17]]},[17]]},[17]]},[2,4,5,6,7,13,14,17,21,22]],"s":[{"i":[{"t":[{"y":[{},[2]]},[2]]},[2]]},[2,16,21]],"e":[{"c":[{"u":[{"r":[{"r":[{"e":[{"n":[{"t":[{},[3]]},[3]]},[3]]},[3]]},[3]]},[3]]},[3]],"n":[{"t":[{"i":[{"a":[{"t":[{"i":[{"o":[{"n":[{":":[{},[15]]},[11,15,23,26]]},[11,15,23,26]]},[11,15,23,26]]},[11,15,23,26]]},[11,15,23,26]]},[11,15,23,26]]},[3,11,15,23,26]]},[3,11,15,23,26]],"v":[{"e":[{"n":[{"t":[{"s":[{},[4]]},[4]]},[4]]},[4]]},[4]],"g":[{"u":[{"l":[{"a":[{"t":[{"o":[{"r":[{"y":[{},[5]],"s":[{},[16]]},[5,16]]},[5,16]],"e":[{"s":[{},[9]]},[9,29]]},[5,9,16,29]]},[5,9,16,29]]},[5,9,16,29]]},[5,9,16,29]]},[5,9,16,29]],"d":[{"e":[{"r":[{"i":[{"c":[{"k":[{},[6]]},[6]]},[6]]},[6]]},[6]],"i":[{"c":[{"t":[{"i":[{"o":[{"n":[{},[14]]},[14]]},[14]]},[14]]},[14]]},[14]]},[6,14,21]],"l":[{"l":[{"i":[{},[6]],"a":[{},[6,24,25]]},[6,24,25]]},[6,24,25]],"i":[{"n":[{"f":[{"o":[{"r":[{"c":[{"e":[{"s":[{},[11]]},[11]]},[11]]},[11]]},[11]]},[11]]},[11]]},[11]],"p":[{"r":[{"e":[{"s":[{"s":[{"i":[{"o":[{"n":[{},[22]]},[22]],"n":[{"g":[{},[31]]},[31]]},[22,31]]},[11,22,31]]},[11,22,31]]},[11,22,31]]},[11,22,31]]},[11,22,31]],"s":[{"s":[{"i":[{"v":[{"e":[{"n":[{"e":[{"s":[{"s":[{},[16]]},[16]]},[16]]},[16]]},[16]]},[16]],"o":[{"n":[{},[22]]},[22]],"n":[{"g":[{},[31]]},[31]]},[16,22,31]]},[11,16,22,31]],"t":[{"‐":[{"m":[{"a":[{"d":[{"2":[{},[27]]},[27]]},[27]]},[27]]},[27]]},[27]]},[11,16,22,27,31]],"h":[{"e":[{"n":[{"s":[{"i":[{"v":[{"e":[{},[14]]},[14]]},[14]]},[14]]},[14]]},[14]]},[14]],"q":[{"u":[{"i":[{"r":[{"e":[{"d":[{},[21]]},[21]]},[21]]},[21]]},[21]]},[21]],"b":[{"e":[{"l":[{"l":[{"u":[{"m":[{},[23]]},[23]]},[23]]},[23]]},[23]]},[23]],"t":[{"i":[{"n":[{"o":[{"b":[{"l":[{"a":[{"s":[{"t":[{"o":[{"m":[{"a":[{},[31,32]]},[31,32]]},[31,32]]},[31,32]]},[31,32]]},[31,32]]},[31,32]]},[31,32]]},[31,32]]},[31,32]]},[31,32]]},[31,32]]},[3,4,5,6,9,11,14,15,16,21,22,23,24,25,26,27,29,31,32]],"r":[{"e":[{"n":[{"t":[{},[3,15]]},[3,15]]},[3,15]]},[3,15]],"k":[{"c":[{"a":[{},[3]]},[3]]},[3]],"d":[{"o":[{"i":[{"d":[{},[3]]},[3]]},[3]]},[3]],"c":[{"i":[{"n":[{"g":[{},[4]]},[4]]},[4]],"e":[{"s":[{},[11]]},[11]],"p":[{"‐":[{"r":[{"e":[{"s":[{"t":[{"‐":[{"m":[{"a":[{"d":[{"2":[{},[27]]},[27]]},[27]]},[27]]},[27]]},[27]]},[27]]},[27]]},[27]]},[27]]},[27]]},[4,11,27]],"t":[{},[5]],"y":[{"t":[{"h":[{"r":[{"o":[{"p":[{"o":[{"i":[{"e":[{"s":[{"i":[{"s":[{},[31]]},[31]]},[31]]},[31]]},[31]]},[31]]},[31]]},[31]]},[31]]},[31]]},[31]]},[5,31]],"u":[{"s":[{"s":[{"o":[{},[6]]},[6]]},[6]],"l":[{"o":[{},[6]]},[6]]},[6]],",":[{},[6]],"m":[{"a":[{"l":[{},[7]],"t":[{"i":[{"o":[{"n":[{},[7,17]]},[7,17]]},[7,17]]},[7,17]]},[7,17]],"i":[{"n":[{"g":[{},[20]]},[20]]},[20]]},[7,17,20]],"-":[{"t":[{"a":[{"c":[{"c":[{},[8,13]]},[8,13]]},[8,13]]},[8,13]]},[8,13]],"h":[{"p":[{"n":[{"2":[{},[17]]},[17]]},[17]],"o":[{"a":[{},[17]]},[17]]},[17]],"g":[{"e":[{"t":[{},[32]]},[29,32]]},[29,32]],"b":[{},[30]]},[]],"s":[{"t":[{"o":[{"m":[{"a":[{"s":[{},[0]]},[0,5,10,20,31,32]]},[0,5,10,20,31,32]],"n":[{"e":[{},[7]]},[7]]},[0,5,7,10,20,31,32]],"a":[{"n":[{"o":[{},[6]]},[6]],"i":[{"n":[{"s":[{},[7]]},[7]]},[7]],"b":[{"i":[{"l":[{"i":[{"z":[{"i":[{"n":[{"g":[{},[26]]},[26]]},[26]]},[26]],"t":[{"y":[{},[27]]},[27]]},[26,27]]},[26,27]]},[26,27]]},[26,27]]},[6,7,26,27]],"e":[{"m":[{"n":[{"e":[{"s":[{"s":[{},[19]]},[19]]},[19]]},[19]]},[9,16,19]],"r":[{},[16]]},[9,16,19]],"‐":[{"m":[{"a":[{"d":[{"2":[{},[27]]},[27]]},[27]]},[27]]},[27]]},[0,5,6,7,9,10,15,16,19,20,26,27,31,32]],"u":[{"r":[{"v":[{"i":[{"v":[{"a":[{"l":[{},[0]]},[0]]},[0]]},[0]]},[0]]},[0]],"s":[{"t":[{"a":[{"i":[{"n":[{"s":[{},[7]]},[7]]},[7]]},[7]]},[7]],":":[{},[14]]},[7,14]]},[0,7,14]],"c":[{"a":[{"p":[{"e":[{},[1]]},[1]],"d":[{"e":[{},[7]]},[7]]},[1,7]],"r":[{"i":[{"p":[{"t":[{"o":[{"m":[{"e":[{},[2]]},[2]]},[2]],"i":[{"o":[{"n":[{"a":[{"l":[{},[22]]},[22]]},[4,21,22]]},[4,21,22]]},[4,21,22]]},[2,4,21,22]]},[2,4,21,22]]},[2,4,21,22]]},[2,4,21,22]],"h":[{},[24]]},[1,2,4,7,21,22,24]],"i":[{"s":[{},[1,2,5,30,31]],"n":[{"g":[{"l":[{"e":[{"-":[{"c":[{"e":[{"l":[{"l":[{},[2]]},[2]]},[2]]},[2]]},[2]]},[2]]},[2]]},[2,31]]},[2,31]],"t":[{"y":[{},[2]],"i":[{"v":[{"e":[{},[5]]},[5]]},[5]]},[2,5]],"o":[{"n":[{"s":[{},[8,13,14,20]]},[8,13,14,20,22]]},[8,13,14,20,22]],"v":[{"e":[{"n":[{"e":[{"s":[{"s":[{},[16]]},[16]]},[16]]},[16]]},[14,16]]},[14,16]],"g":[{"n":[{"a":[{"l":[{"l":[{"i":[{"n":[{"g":[{},[32]]},[32]]},[32]]},[32]]},[32]]},[32]]},[32]]},[32]]},[1,2,5,8,13,14,16,20,22,30,31,32]],"s":[{"-":[{"c":[{"o":[{"h":[{"o":[{"r":[{"t":[{},[5]]},[5]]},[5]]},[5]]},[5]]},[5]]},[5]],"o":[{},[6]],"i":[{"v":[{"e":[{"n":[{"e":[{"s":[{"s":[{},[16]]},[16]]},[16]]},[16]]},[16]]},[16]],"o":[{"n":[{},[22]]},[22]],"n":[{"g":[{},[31]]},[31]]},[16,22,31]],"e":[{"n":[{"t":[{"i":[{"a":[{"l":[{},[23]]},[23]]},[23]]},[23]]},[23]]},[23]]},[5,6,11,16,19,22,23,31]],"-":[{"c":[{"o":[{"h":[{"o":[{"r":[{"t":[{},[5]]},[5]]},[5]]},[5]]},[5]]},[5]]},[5]],"k":[{},[5]],"m":[{",":[{},[6]]},[6,12]],"o":[{"n":[{},[6]],"r":[{"e":[{"l":[{"l":[{"a":[{},[6,24,25]]},[6,24,25]]},[6,24,25]]},[6,24,25]]},[6,24,25]],"m":[{"e":[{},[27]]},[27]]},[6,24,25,27]],"b":[{",":[{},[6]]},[6]],"h":[{"i":[{},[6]]},[6]],"a":[{"n":[{"s":[{"o":[{"n":[{},[6]]},[6]]},[6]]},[6]]},[6]],"j":[{",":[{},[6]]},[6]],"f":[{"o":[{"r":[{"m":[{"a":[{"t":[{"i":[{"o":[{"n":[{},[7,17]]},[7,17]]},[7,17]]},[7,17]]},[7,17]],"i":[{"n":[{"g":[{},[20]]},[20]]},[20]]},[7,17,20]]},[7,17,20]]},[7,17,20]]},[7,17,20]],"e":[{"n":[{"c":[{"h":[{"y":[{"m":[{"a":[{"l":[{},[17,18]]},[17,18]]},[17,18]]},[17,18]]},[17,18]]},[17,18]],"t":[{"i":[{"a":[{"l":[{},[23]]},[23]]},[23]]},[23]]},[17,18,23]],"m":[{"a":[{"p":[{"h":[{"o":[{"r":[{"i":[{"n":[{},[22]]},[22]]},[22]]},[22]]},[22]]},[22]]},[22]]},[22]]},[9,17,18,22,23,26,28]],":":[{},[14,16]],"y":[{"n":[{"c":[{"h":[{"r":[{"o":[{"n":[{"i":[{"z":[{"e":[{},[19,23]]},[19,23]]},[19,23]]},[19,23]]},[19,23]]},[19,23]]},[19,23]]},[19,23]]},[19,23]]},[19,23]],",":[{},[25]]},[]],"w":[{"i":[{"t":[{"h":[{},[0,1]]},[0,1]],"s":[{},[6]],"l":[{"d":[{"-":[{"t":[{"y":[{"p":[{"e":[{},[13]]},[13]]},[13]]},[13]]},[13]]},[13]]},[13]],"g":[{},[25]]},[0,1,6,13,25]],"e":[{"1":[{},[7,9,23,26]]},[7,9,23,26]],"t":[{"h":[{},[7,28]]},[7,28]]},[]],"v":[{"i":[{"v":[{"a":[{"l":[{},[0]]},[0]]},[0]]},[0]],"a":[{"l":[{},[0]],"r":[{"o":[{"n":[{"e":[{},[6,24,25]]},[6,24,25]]},[6,24,25]],"i":[{"a":[{"n":[{},[7]]},[7]]},[7]]},[6,7,24,25]],"t":[{"i":[{"o":[{"n":[{},[12,17]]},[12,17]]},[12,17]]},[12,17]],"s":[{"i":[{"o":[{"n":[{},[22]]},[22]]},[22]]},[22]]},[0,6,7,12,17,22,24,25]],"e":[{"r":[{"s":[{"i":[{"t":[{"y":[{},[2]]},[2]]},[2]]},[2]],"g":[{"e":[{},[29]]},[29]]},[2,14,29,31]],"n":[{"t":[{"s":[{},[4]]},[4]],"e":[{"s":[{"s":[{},[16]]},[16]]},[16]]},[4,16]],"l":[{"o":[{"p":[{"m":[{"e":[{"n":[{"t":[{},[4,21]]},[4,21]]},[4,21]]},[4,21]],"i":[{"n":[{"g":[{},[23]]},[23]]},[23]]},[4,21,23]]},[4,21,23]]},[4,21,23]],"s":[{},[17]]},[2,4,5,14,16,17,21,23,29,31]],",":[{},[6]],"o":[{"l":[{"u":[{"t":[{"i":[{"o":[{"n":[{},[10]]},[10]]},[10]]},[10]]},[10]]},[10]]},[10]],"h":[{"l":[{},[12]]},[12]]},[]],"-":[{"c":[{"e":[{"l":[{"l":[{},[2]]},[2]]},[2]],"o":[{"h":[{"o":[{"r":[{"t":[{},[5]]},[5]]},[5]]},[5]]},[5]]},[2,5]],"g":[{"r":[{"a":[{"d":[{"e":[{},[2,18]]},[2,18]]},[2,18]]},[2,18]]},[2,18]],"m":[{"y":[{"c":[{"n":[{},[5]]},[5]]},[5]]},[5]],"r":[{"i":[{"s":[{"k":[{},[5]]},[5]]},[5]],"a":[{"p":[{"1":[{},[18]]},[18]]},[18]]},[5,18]],"j":[{"o":[{"h":[{"n":[{"s":[{"o":[{"n":[{},[6]]},[6]]},[6]]},[6]]},[6]]},[6]]},[6]],"h":[{"1":[{"9":[{},[7]]},[7]]},[7]],"t":[{"a":[{"c":[{"c":[{},[8,13]]},[8,13]]},[8,13]],"y":[{"p":[{"e":[{},[13]]},[13]]},[13]]},[8,13]],"d":[{"e":[{"p":[{"e":[{"n":[{"d":[{"e":[{"n":[{"t":[{},[12]]},[12]]},[12]]},[12]]},[12]]},[12]]},[12]]},[12]]},[12]]},[]],"k":[{"c":[{"a":[{},[3]]},[3]],"h":[{"t":[{"a":[{"r":[{"i":[{},[6]]},[6]]},[6]]},[6]]},[6]],",":[{},[6,24,25]],"s":[{"j":[{",":[{},[6]]},[6]]},[6]],"i":[{"p":[{"2":[{},[29]]},[29]]},[29]]},[]],"ï":[{"v":[{"e":[{},[4]]},[4]]},[]],",":[{},[]],"j":[{"j":[{",":[{},[6]]},[6]],",":[{},[6]],"o":[{"h":[{"n":[{"s":[{"o":[{"n":[{},[6]]},[6]]},[6]]},[6]]},[6]]},[6]]},[]],"z":[{"h":[{"a":[{"n":[{"g":[{},[6]]},[6]]},[6]]},[6]],"a":[{"t":[{"i":[{"o":[{"n":[{",":[{},[13]]},[13]]},[13]]},[13]]},[13]]},[13]],"e":[{},[19,23]],"i":[{"n":[{"g":[{},[26]]},[26]]},[26]]},[]],"x":[{",":[{},[6]],"i":[{"s":[{},[18,27]],"t":[{},[28]]},[18,27,28]],"o":[{"n":[{"a":[{"l":[{},[28]]},[28]]},[28]]},[28]]},[]],".":[{"3":[{"-":[{"h":[{"1":[{"9":[{},[7]]},[7]]},[7]]},[7]]},[7]]},[]],":":[{},[]],"(":[{"+":[{")":[{},[21]]},[21]]},[]],"+":[{")":[{},[21]]},[]],")":[{},[]],"‐":[{"d":[{"o":[{"m":[{"a":[{"i":[{"n":[{},[26]]},[26]]},[26]]},[26]]},[26]]},[26]],"m":[{"y":[{"c":[{"o":[{"n":[{"c":[{"o":[{"p":[{"r":[{"o":[{"t":[{"e":[{"i":[{"n":[{},[26]]},[26]]},[26]]},[26]]},[26]]},[26]]},[26]]},[26]]},[26]]},[26]]},[26]]},[26]]},[26]],"a":[{"d":[{"2":[{},[27]]},[27]]},[27]]},[26,27]],"t":[{"r":[{"c":[{"p":[{"‐":[{"r":[{"e":[{"s":[{"t":[{"‐":[{"m":[{"a":[{"d":[{"2":[{},[27]]},[27]]},[27]]},[27]]},[27]]},[27]]},[27]]},[27]]},[27]]},[27]]},[27]]},[27]]},[27]]},[27]],"r":[{"e":[{"s":[{"t":[{"‐":[{"m":[{"a":[{"d":[{"2":[{},[27]]},[27]]},[27]]},[27]]},[27]]},[27]]},[27]]},[27]]},[27]]},[]]},[]]